<?xml version="1.0" encoding="UTF-8"?>
<openmensa version="2.1"
           xmlns="http://openmensa.org/open-mensa-v2"
           xmlns:xsi="http://www.w3.org/2001/XMLSchema-instance"
           xsi:schemaLocation="http://openmensa.org/open-mensa-v2 http://openmensa.org/open-mensa-v2.xsd">
  <canteen>
    <day date="2018-04-17">
      <category name="Salate">
        <meal>
          <name>Große Salatschale</name>
          <note>grün (Ampel)</note>
          <note>vegan</note>
          <note>Süßungsmittel</note>
          <note>Sellerie</note>
          <price role="student">1.65</price>
          <price role="employee">3.30</price>
          <price role="other">3.65</price>
        </meal>
        <meal>
          <name>Kleine Salatschale</name>
          <note>grün (Ampel)</note>
          <note>vegan</note>
          <note>Süßungsmittel</note>
          <note>Sellerie</note>
          <price role="student">0.60</price>
          <price role="employee">1.20</price>
          <price role="other">1.30</price>
        </meal>
      </category>
      <category name="Aktionen">
        <meal>
          <name>Quarkbecher mit Früchten</name>
          <note>gelb (Ampel)</note>
          <note>vegetarisch</note>
          <note>Antioxidationsmittel</note>
          <note>Milch und Milchprodukte (inkl. Laktose)</note>
          <price role="student">1.45</price>
          <price role="employee">1.45</price>
          <price role="other">1.45</price>
        </meal>
        <meal>
          <name>Joghurtbecher mit Früchten</name>
          <note>grün (Ampel)</note>
          <note>vegetarisch</note>
          <note>Antioxidationsmittel</note>
          <note>Milch und Milchprodukte (inkl. Laktose)</note>
          <price role="student">1.45</price>
          <price role="employee">1.45</price>
          <price role="other">1.45</price>
        </meal>
      </category>
      <category name="Essen">
        <meal>
          <name>Lammgulasch mit Paprika, Oliven und mediterranen Kräutern</name>
          <note>gelb (Ampel)</note>
          <note>geschwärzt</note>
          <note>Senf</note>
          <price role="student">2.45</price>
          <price role="employee">4.90</price>
          <price role="other">5.40</price>
        </meal>
        <meal>
          <name>Eine geschmorte Rinderroulade mit Speck an Gemüsesauce</name>
          <note>gelb (Ampel)</note>
          <note>Schweinefleisch bzw. mit Gelatine vom Schwein</note>
          <note>Süßungsmittel</note>
          <note>Sellerie</note>
          <note>Senf</note>
          <price role="student">2.45</price>
          <price role="employee">4.90</price>
          <price role="other">5.40</price>
        </meal>
        <meal>
          <name>Vollkornspiralnudeln mit Tomatensauce und gerösteten Haselnüssen</name>
          <note>grün (Ampel)</note>
          <note>vegan</note>
          <note>Klimaessen</note>
          <note>Weizen</note>
          <note>Haselnuss</note>
          <price role="student">1.75</price>
          <price role="employee">3.50</price>
          <price role="other">3.85</price>
        </meal>
        <meal>
          <name>Süßkartoffelauflauf</name>
          <note>grün (Ampel)</note>
          <note>vegetarisch</note>
          <note>Eier</note>
          <note>Milch und Milchprodukte (inkl. Laktose)</note>
          <price role="student">1.35</price>
          <price role="employee">2.70</price>
          <price role="other">2.95</price>
        </meal>
      </category>
      <category name="Beilagen">
        <meal>
          <name>Apfelrotkohl</name>
          <note>grün (Ampel)</note>
          <note>vegan</note>
          <note>Antioxidationsmittel</note>
          <note>Schwefeldioxid und Sulfide</note>
          <price role="student">0.55</price>
          <price role="employee">1.10</price>
          <price role="other">1.20</price>
        </meal>
        <meal>
          <name>Petersilienkartoffeln</name>
          <note>grün (Ampel)</note>
          <note>vegan</note>
          <price role="student">0.55</price>
          <price role="employee">1.10</price>
          <price role="other">1.20</price>
        </meal>
        <meal>
          <name>Eierspätzle</name>
          <note>gelb (Ampel)</note>
          <note>vegetarisch</note>
          <note>Eier</note>
          <note>Weizen</note>
          <price role="student">0.55</price>
          <price role="employee">1.10</price>
          <price role="other">1.20</price>
        </meal>
        <meal>
          <name>Gemüsesauce</name>
          <note>gelb (Ampel)</note>
          <note>Süßungsmittel</note>
          <note>Sellerie</note>
          <note>Senf</note>
          <price role="student">0.25</price>
          <price role="employee">0.50</price>
          <price role="other">0.55</price>
        </meal>
      </category>
      <category name="Desserts">
        <meal>
          <name>Vanillequark</name>
          <note>grün (Ampel)</note>
          <note>vegetarisch</note>
          <note>Milch und Milchprodukte (inkl. Laktose)</note>
          <price role="student">0.60</price>
          <price role="employee">1.20</price>
          <price role="other">1.30</price>
        </meal>
      </category>
    </day>
    <day date="2018-04-18">
      <category name="Salate">
        <meal>
          <name>Große Salatschale</name>
          <note>grün (Ampel)</note>
          <note>vegan</note>
          <note>Süßungsmittel</note>
          <note>Sellerie</note>
          <price role="student">1.65</price>
          <price role="employee">3.30</price>
          <price role="other">3.65</price>
        </meal>
        <meal>
          <name>Kleine Salatschale</name>
          <note>grün (Ampel)</note>
          <note>vegan</note>
          <note>Süßungsmittel</note>
          <note>Sellerie</note>
          <price role="student">0.60</price>
          <price role="employee">1.20</price>
          <price role="other">1.30</price>
        </meal>
      </category>
      <category name="Aktionen">
        <meal>
          <name>Joghurtbecher mit Früchten</name>
          <note>grün (Ampel)</note>
          <note>vegetarisch</note>
          <note>Antioxidationsmittel</note>
          <note>Milch und Milchprodukte (inkl. Laktose)</note>
          <price role="student">1.45</price>
          <price role="employee">1.45</price>
          <price role="other">1.45</price>
        </meal>
        <meal>
          <name>Quarkbecher mit Früchten</name>
          <note>gelb (Ampel)</note>
          <note>vegetarisch</note>
          <note>Antioxidationsmittel</note>
          <note>Milch und Milchprodukte (inkl. Laktose)</note>
          <price role="student">1.45</price>
          <price role="employee">1.45</price>
          <price role="other">1.45</price>
        </meal>
      </category>
      <category name="Essen">
        <meal>
          <name>Ein gebackenes Forellenfilet in Mandelpanade an Kerbelrahmsauce</name>
          <note>gelb (Ampel)</note>
          <note>Antioxidationsmittel</note>
          <note>Fisch</note>
          <note>Sellerie</note>
          <note>Milch und Milchprodukte (inkl. Laktose)</note>
          <note>Schwefeldioxid und Sulfide</note>
          <note>Weizen</note>
          <note>Mandeln</note>
          <price role="student">1.95</price>
          <price role="employee">3.90</price>
          <price role="other">4.30</price>
        </meal>
        <meal>
          <name>Kürbis-Chiasamen-Bratling an Zitronen-Kurkuma-Sauce</name>
          <note>gelb (Ampel)</note>
          <note>vegan</note>
          <note>Antioxidationsmittel</note>
          <note>Farbstoff</note>
          <note>Soja</note>
          <price role="student">1.25</price>
          <price role="employee">2.50</price>
          <price role="other">2.75</price>
        </meal>
        <meal>
          <name>Hühnersuppentopf mit Reis</name>
          <note>grün (Ampel)</note>
          <note>Antioxidationsmittel</note>
          <note>Eier</note>
          <note>Sellerie</note>
          <note>Milch und Milchprodukte (inkl. Laktose)</note>
          <price role="student">1.35</price>
          <price role="employee">2.70</price>
          <price role="other">2.95</price>
        </meal>
        <meal>
          <name>Zwei Tiroler Topfenknödel mit Rosinen und Apfel-Vanillesauce</name>
          <note>gelb (Ampel)</note>
          <note>vegetarisch</note>
          <note>Alkohol</note>
          <note>Antioxidationsmittel</note>
          <note>Eier</note>
          <note>Milch und Milchprodukte (inkl. Laktose)</note>
          <note>Hefe</note>
          <note>Weizen</note>
          <price role="student">1.35</price>
          <price role="employee">2.70</price>
          <price role="other">2.95</price>
        </meal>
      </category>
      <category name="Beilagen">
        <meal>
          <name>Zweierlei Karotten</name>
          <note>grün (Ampel)</note>
          <note>vegan</note>
          <price role="student">0.55</price>
          <price role="employee">1.10</price>
          <price role="other">1.20</price>
        </meal>
        <meal>
          <name>Kartoffel-Kräuter-Püree</name>
          <note>gelb (Ampel)</note>
          <note>vegetarisch</note>
          <note>konserviert</note>
          <note>Antioxidationsmittel</note>
          <note>Phosphat</note>
          <note>Milch und Milchprodukte (inkl. Laktose)</note>
          <note>Lupine</note>
          <price role="student">0.70</price>
          <price role="employee">1.40</price>
          <price role="other">1.55</price>
        </meal>
        <meal>
          <name>Kräuterreis</name>
          <note>gelb (Ampel)</note>
          <note>vegan</note>
          <price role="student">0.55</price>
          <price role="employee">1.10</price>
          <price role="other">1.20</price>
        </meal>
        <meal>
          <name>Kerbelrahmsauce</name>
          <note>rot (Ampel)</note>
          <note>Antioxidationsmittel</note>
          <note>Fisch</note>
          <note>Sellerie</note>
          <note>Milch und Milchprodukte (inkl. Laktose)</note>
          <note>Schwefeldioxid und Sulfide</note>
          <note>Weizen</note>
          <price role="student">0.25</price>
          <price role="employee">0.50</price>
          <price role="other">0.55</price>
        </meal>
      </category>
    </day>
    <day date="2018-04-19">
      <category name="Salate">
        <meal>
          <name>Große Salatschale</name>
          <note>grün (Ampel)</note>
          <note>vegan</note>
          <note>Süßungsmittel</note>
          <note>Sellerie</note>
          <price role="student">1.65</price>
          <price role="employee">3.30</price>
          <price role="other">3.65</price>
        </meal>
        <meal>
          <name>Kleine Salatschale</name>
          <note>grün (Ampel)</note>
          <note>vegan</note>
          <note>Süßungsmittel</note>
          <note>Sellerie</note>
          <price role="student">0.60</price>
          <price role="employee">1.20</price>
          <price role="other">1.30</price>
        </meal>
      </category>
      <category name="Aktionen">
        <meal>
          <name>Quarkbecher mit Früchten</name>
          <note>gelb (Ampel)</note>
          <note>vegetarisch</note>
          <note>Antioxidationsmittel</note>
          <note>Milch und Milchprodukte (inkl. Laktose)</note>
          <price role="student">1.45</price>
          <price role="employee">1.45</price>
          <price role="other">1.45</price>
        </meal>
        <meal>
          <name>Joghurtbecher mit Früchten</name>
          <note>grün (Ampel)</note>
          <note>vegetarisch</note>
          <note>Antioxidationsmittel</note>
          <note>Milch und Milchprodukte (inkl. Laktose)</note>
          <price role="student">1.45</price>
          <price role="employee">1.45</price>
          <price role="other">1.45</price>
        </meal>
        <meal>
          <name>Hamburger im Sesambrötchen mit Pommes frites und Salat</name>
          <note>gelb (Ampel)</note>
          <note>konserviert</note>
          <note>Süßungsmittel</note>
          <note>mit zum Teil fein zerkleinertem Fleischanteil</note>
          <note>Eier</note>
          <note>Sellerie</note>
          <note>Soja</note>
          <note>Senf</note>
          <note>Sesam</note>
          <note>Hefe</note>
          <note>Weizen</note>
          <price role="student">4.95</price>
          <price role="employee">4.95</price>
          <price role="other">4.95</price>
        </meal>
      </category>
      <category name="Essen">
        <meal>
          <name>Ein gebackener Selleriebratling an Kürbis-Sesam-Sauce</name>
          <note>gelb (Ampel)</note>
          <note>vegan</note>
          <note>konserviert</note>
          <note>Antioxidationsmittel</note>
          <note>Sellerie</note>
          <note>Soja</note>
          <note>Sesam</note>
          <note>Hefe</note>
          <note>Weizen</note>
          <price role="student">1.25</price>
          <price role="employee">2.50</price>
          <price role="other">2.75</price>
        </meal>
        <meal>
          <name>Hoppel-Poppel - Berliner Kartoffelauflauf mit Magerspeck, Zwiebeln und Ei</name>
          <note>gelb (Ampel)</note>
          <note>Schweinefleisch bzw. mit Gelatine vom Schwein</note>
          <note>konserviert</note>
          <note>Antioxidationsmittel</note>
          <note>Phosphat</note>
          <note>Eier</note>
          <note>Nitritpökelsalz</note>
          <price role="student">1.35</price>
          <price role="employee">2.70</price>
          <price role="other">2.95</price>
        </meal>
        <meal>
          <name>Sahniger Milchreis mit Zimt, Zucker und Rhabarber-Himbeer-Sauce</name>
          <note>gelb (Ampel)</note>
          <note>vegetarisch</note>
          <note>Farbstoff</note>
          <note>Milch und Milchprodukte (inkl. Laktose)</note>
          <price role="student">1.35</price>
          <price role="employee">2.70</price>
          <price role="other">2.95</price>
        </meal>
      </category>
      <category name="Beilagen">
        <meal>
          <name>Mediterranes Gemüse</name>
          <note>grün (Ampel)</note>
          <note>vegetarisch</note>
          <note>Farbstoff</note>
          <note>Schwefeldioxid und Sulfide</note>
          <price role="student">0.55</price>
          <price role="employee">1.10</price>
          <price role="other">1.20</price>
        </meal>
        <meal>
          <name>Pommes frites</name>
          <note>gelb (Ampel)</note>
          <note>vegan</note>
          <price role="student">0.70</price>
          <price role="employee">1.40</price>
          <price role="other">1.55</price>
        </meal>
        <meal>
          <name>Vollkornspiralnudeln</name>
          <note>grün (Ampel)</note>
          <note>vegan</note>
          <note>Weizen</note>
          <price role="student">0.55</price>
          <price role="employee">1.10</price>
          <price role="other">1.20</price>
        </meal>
        <meal>
          <name>Kürbis-Sesam-Sauce</name>
          <note>gelb (Ampel)</note>
          <note>vegan</note>
          <note>konserviert</note>
          <note>Antioxidationsmittel</note>
          <note>Soja</note>
          <note>Sesam</note>
          <price role="student">0.25</price>
          <price role="employee">0.50</price>
          <price role="other">0.55</price>
        </meal>
      </category>
    </day>
    <day date="2018-04-20">
      <category name="Salate">
        <meal>
          <name>Große Salatschale</name>
          <note>grün (Ampel)</note>
          <note>vegan</note>
          <note>Süßungsmittel</note>
          <note>Sellerie</note>
          <price role="student">1.65</price>
          <price role="employee">3.30</price>
          <price role="other">3.65</price>
        </meal>
        <meal>
          <name>Kleine Salatschale</name>
          <note>grün (Ampel)</note>
          <note>vegan</note>
          <note>Süßungsmittel</note>
          <note>Sellerie</note>
          <price role="student">0.60</price>
          <price role="employee">1.20</price>
          <price role="other">1.30</price>
        </meal>
      </category>
      <category name="Aktionen">
        <meal>
          <name>Pfannenfrische Gnocchi mit Schluppen und Gorgonzola-Chili-Sauce</name>
          <note>gelb (Ampel)</note>
          <note>konserviert</note>
          <note>Milch und Milchprodukte (inkl. Laktose)</note>
          <note>Weizen</note>
          <price role="student">2.95</price>
          <price role="employee">2.95</price>
          <price role="other">2.95</price>
        </meal>
        <meal>
          <name>Quarkbecher mit Früchten</name>
          <note>gelb (Ampel)</note>
          <note>vegetarisch</note>
          <note>Antioxidationsmittel</note>
          <note>Milch und Milchprodukte (inkl. Laktose)</note>
          <price role="student">1.45</price>
          <price role="employee">1.45</price>
          <price role="other">1.45</price>
        </meal>
        <meal>
          <name>Joghurtbecher mit Früchten</name>
          <note>grün (Ampel)</note>
          <note>vegetarisch</note>
          <note>Antioxidationsmittel</note>
          <note>Milch und Milchprodukte (inkl. Laktose)</note>
          <price role="student">1.45</price>
          <price role="employee">1.45</price>
          <price role="other">1.45</price>
        </meal>
      </category>
      <category name="Essen">
        <meal>
          <name>Ein gebackenes Seelachsfilet an Tatarensauce</name>
          <note>rot (Ampel)</note>
          <note>MSC</note>
          <note>Süßungsmittel</note>
          <note>Eier</note>
          <note>Sellerie</note>
          <note>Senf</note>
          <note>Milch und Milchprodukte (inkl. Laktose)</note>
          <note>Hefe</note>
          <note>Weizen</note>
          <price role="student">1.45</price>
          <price role="employee">2.90</price>
          <price role="other">3.20</price>
        </meal>
        <meal>
          <name>Bohnensuppe nach Toskanischer Art</name>
          <note>grün (Ampel)</note>
          <note>vegan</note>
          <note>Sellerie</note>
          <price role="student">1.35</price>
          <price role="employee">2.70</price>
          <price role="other">2.95</price>
        </meal>
      </category>
      <category name="Beilagen">
        <meal>
          <name>Leipziger Allerlei</name>
          <note>grün (Ampel)</note>
          <note>vegan</note>
          <price role="student">0.55</price>
          <price role="employee">1.10</price>
          <price role="other">1.20</price>
        </meal>
        <meal>
          <name>Rosmarinkartoffeln</name>
          <note>grün (Ampel)</note>
          <note>vegan</note>
          <price role="student">0.70</price>
          <price role="employee">1.40</price>
          <price role="other">1.55</price>
        </meal>
        <meal>
          <name>Langkornreis mit Wildreis</name>
          <note>gelb (Ampel)</note>
          <note>vegan</note>
          <price role="student">0.55</price>
          <price role="employee">1.10</price>
          <price role="other">1.20</price>
        </meal>
        <meal>
          <name>Tatarensauce</name>
          <note>rot (Ampel)</note>
          <note>vegetarisch</note>
          <note>Süßungsmittel</note>
          <note>Eier</note>
          <note>Sellerie</note>
          <note>Senf</note>
          <note>Milch und Milchprodukte (inkl. Laktose)</note>
          <note>Weizen</note>
          <price role="student">0.25</price>
          <price role="employee">0.50</price>
          <price role="other">0.55</price>
        </meal>
      </category>
    </day>
    <day date="2018-04-21">
      <closed></closed>
    </day>
    <day date="2018-04-22">
      <closed></closed>
    </day>
    <day date="2018-04-23">
      <category name="Salate">
        <meal>
          <name>Große Salatschale</name>
          <note>grün (Ampel)</note>
          <note>vegan</note>
          <note>Süßungsmittel</note>
          <note>Sellerie</note>
          <price role="student">1.65</price>
          <price role="employee">3.30</price>
          <price role="other">3.65</price>
        </meal>
        <meal>
          <name>Kleine Salatschale</name>
          <note>grün (Ampel)</note>
          <note>vegan</note>
          <note>Süßungsmittel</note>
          <note>Sellerie</note>
          <price role="student">0.60</price>
          <price role="employee">1.20</price>
          <price role="other">1.30</price>
        </meal>
      </category>
      <category name="Aktionen">
        <meal>
          <name>Quarkbecher mit Früchten</name>
          <note>gelb (Ampel)</note>
          <note>vegetarisch</note>
          <note>Antioxidationsmittel</note>
          <note>Milch und Milchprodukte (inkl. Laktose)</note>
          <price role="student">1.45</price>
          <price role="employee">1.45</price>
          <price role="other">1.45</price>
        </meal>
        <meal>
          <name>Joghurtbecher mit Früchten</name>
          <note>grün (Ampel)</note>
          <note>vegetarisch</note>
          <note>Antioxidationsmittel</note>
          <note>Milch und Milchprodukte (inkl. Laktose)</note>
          <price role="student">1.45</price>
          <price role="employee">1.45</price>
          <price role="other">1.45</price>
        </meal>
      </category>
      <category name="Essen">
        <meal>
          <name>Quinoa-Chili-Medaillon an Kokos-Karotten-Sauce</name>
          <note>gelb (Ampel)</note>
          <note>vegetarisch</note>
          <note>Farbstoff</note>
          <note>Eier</note>
          <note>Milch und Milchprodukte (inkl. Laktose)</note>
          <note>Hefe</note>
          <note>Weizen</note>
          <price role="student">1.75</price>
          <price role="employee">3.50</price>
          <price role="other">3.85</price>
        </meal>
        <meal>
          <name>Eine gebackene Hähnchenbrust im Knuspermantel an Geflügelrahmsauce</name>
          <note>rot (Ampel)</note>
          <note>Milch und Milchprodukte (inkl. Laktose)</note>
          <note>Hefe</note>
          <note>Weizen</note>
          <price role="student">1.45</price>
          <price role="employee">2.90</price>
          <price role="other">3.20</price>
        </meal>
        <meal>
          <name>Berliner Erbseneintopf mit Wurzelgemüse und frischer Blattpetersilie und einer Geflügelwiener</name>
          <note>gelb (Ampel)</note>
          <note>konserviert</note>
          <note>Antioxidationsmittel</note>
          <note>Sellerie</note>
          <note>Senf</note>
          <note>Nitritpökelsalz</note>
          <price role="student">1.35</price>
          <price role="employee">2.70</price>
          <price role="other">2.95</price>
        </meal>
      </category>
      <category name="Beilagen">
        <meal>
          <name>Blumenkohl</name>
          <note>grün (Ampel)</note>
          <note>vegan</note>
          <price role="student">0.55</price>
          <price role="employee">1.10</price>
          <price role="other">1.20</price>
        </meal>
        <meal>
          <name>Schwenkkartoffeln</name>
          <note>gelb (Ampel)</note>
          <note>vegan</note>
          <price role="student">0.70</price>
          <price role="employee">1.40</price>
          <price role="other">1.55</price>
        </meal>
        <meal>
          <name>Parboiledreis</name>
          <note>gelb (Ampel)</note>
          <note>vegan</note>
          <price role="student">0.55</price>
          <price role="employee">1.10</price>
          <price role="other">1.20</price>
        </meal>
        <meal>
          <name>Kokos-Karotten-Sauce</name>
          <note>gelb (Ampel)</note>
          <note>vegan</note>
          <price role="student">0.25</price>
          <price role="employee">0.50</price>
          <price role="other">0.55</price>
        </meal>
        <meal>
          <name>Geflügelrahmsauce</name>
          <note>gelb (Ampel)</note>
          <note>Milch und Milchprodukte (inkl. Laktose)</note>
          <price role="student">0.25</price>
          <price role="employee">0.50</price>
          <price role="other">0.55</price>
        </meal>
      </category>
    </day>
    <day date="2018-04-24">
      <category name="Salate">
        <meal>
          <name>Große Salatschale</name>
          <note>grün (Ampel)</note>
          <note>vegan</note>
          <note>Süßungsmittel</note>
          <note>Sellerie</note>
          <price role="student">1.65</price>
          <price role="employee">3.30</price>
          <price role="other">3.65</price>
        </meal>
        <meal>
          <name>Kleine Salatschale</name>
          <note>grün (Ampel)</note>
          <note>vegan</note>
          <note>Süßungsmittel</note>
          <note>Sellerie</note>
          <price role="student">0.60</price>
          <price role="employee">1.20</price>
          <price role="other">1.30</price>
        </meal>
      </category>
      <category name="Aktionen">
        <meal>
          <name>Joghurtbecher mit Früchten</name>
          <note>grün (Ampel)</note>
          <note>vegetarisch</note>
          <note>Antioxidationsmittel</note>
          <note>Milch und Milchprodukte (inkl. Laktose)</note>
          <price role="student">1.45</price>
          <price role="employee">1.45</price>
          <price role="other">1.45</price>
        </meal>
        <meal>
          <name>Quarkbecher mit Früchten</name>
          <note>gelb (Ampel)</note>
          <note>vegetarisch</note>
          <note>Antioxidationsmittel</note>
          <note>Milch und Milchprodukte (inkl. Laktose)</note>
          <price role="student">1.45</price>
          <price role="employee">1.45</price>
          <price role="other">1.45</price>
        </meal>
      </category>
      <category name="Essen">
        <meal>
          <name>Ein Putenbrustspieß Picanto an Paprikasauce</name>
          <note>gelb (Ampel)</note>
          <note>Antioxidationsmittel</note>
          <note>Senf</note>
          <price role="student">1.95</price>
          <price role="employee">3.90</price>
          <price role="other">4.30</price>
        </meal>
        <meal>
          <name>Eine Bratwurst Thüringer Art an Zwiebel-Kümmel-Jus</name>
          <note>rot (Ampel)</note>
          <note>Schweinefleisch bzw. mit Gelatine vom Schwein</note>
          <note>Senf</note>
          <note>Milch und Milchprodukte (inkl. Laktose)</note>
          <price role="student">1.45</price>
          <price role="employee">2.90</price>
          <price role="other">3.20</price>
        </meal>
        <meal>
          <name>Italienisches Tomaten-Basilikum-Risotto</name>
          <note>gelb (Ampel)</note>
          <note>konserviert</note>
          <note>Eier</note>
          <note>Milch und Milchprodukte (inkl. Laktose)</note>
          <price role="student">1.35</price>
          <price role="employee">2.70</price>
          <price role="other">2.95</price>
        </meal>
      </category>
      <category name="Beilagen">
        <meal>
          <name>Sauerkraut</name>
          <note>grün (Ampel)</note>
          <note>vegan</note>
          <note>Schwefeldioxid und Sulfide</note>
          <price role="student">0.55</price>
          <price role="employee">1.10</price>
          <price role="other">1.20</price>
        </meal>
        <meal>
          <name>Fingermöhren</name>
          <note>grün (Ampel)</note>
          <note>vegan</note>
          <price role="student">0.55</price>
          <price role="employee">1.10</price>
          <price role="other">1.20</price>
        </meal>
        <meal>
          <name>Petersilienkartoffeln</name>
          <note>grün (Ampel)</note>
          <note>vegan</note>
          <price role="student">0.55</price>
          <price role="employee">1.10</price>
          <price role="other">1.20</price>
        </meal>
        <meal>
          <name>Butterreis</name>
          <note>gelb (Ampel)</note>
          <note>vegetarisch</note>
          <note>Milch und Milchprodukte (inkl. Laktose)</note>
          <price role="student">0.55</price>
          <price role="employee">1.10</price>
          <price role="other">1.20</price>
        </meal>
        <meal>
          <name>Zwiebel-Kümmel-Jus</name>
          <note>gelb (Ampel)</note>
          <note>Senf</note>
          <price role="student">0.25</price>
          <price role="employee">0.50</price>
          <price role="other">0.55</price>
        </meal>
        <meal>
          <name>Paprikasauce</name>
          <note>grün (Ampel)</note>
          <note>Senf</note>
          <price role="student">0.25</price>
          <price role="employee">0.50</price>
          <price role="other">0.55</price>
        </meal>
      </category>
    </day>
    <day date="2018-04-25">
      <category name="Salate">
        <meal>
          <name>Große Salatschale</name>
          <note>grün (Ampel)</note>
          <note>vegan</note>
          <note>Süßungsmittel</note>
          <note>Sellerie</note>
          <price role="student">1.65</price>
          <price role="employee">3.30</price>
          <price role="other">3.65</price>
        </meal>
        <meal>
          <name>Kleine Salatschale</name>
          <note>grün (Ampel)</note>
          <note>vegan</note>
          <note>Süßungsmittel</note>
          <note>Sellerie</note>
          <price role="student">0.60</price>
          <price role="employee">1.20</price>
          <price role="other">1.30</price>
        </meal>
      </category>
      <category name="Aktionen">
        <meal>
          <name>Fettuccine mit Brokkoli-Gorgonzola-Sauce</name>
          <note>grün (Ampel)</note>
          <note>Eier</note>
          <note>Sellerie</note>
          <note>Milch und Milchprodukte (inkl. Laktose)</note>
          <note>Weizen</note>
          <price role="student">3.95</price>
          <price role="employee">3.95</price>
          <price role="other">3.95</price>
        </meal>
        <meal>
          <name>Obstsalat</name>
          <note>grün (Ampel)</note>
          <note>vegan</note>
          <note>Antioxidationsmittel</note>
          <price role="student">1.45</price>
          <price role="employee">1.45</price>
          <price role="other">1.45</price>
        </meal>
        <meal>
          <name>Quarkbecher mit Früchten</name>
          <note>gelb (Ampel)</note>
          <note>vegetarisch</note>
          <note>Antioxidationsmittel</note>
          <note>Milch und Milchprodukte (inkl. Laktose)</note>
          <price role="student">1.45</price>
          <price role="employee">1.45</price>
          <price role="other">1.45</price>
        </meal>
      </category>
      <category name="Essen">
        <meal>
          <name>Eine gebackene China-Knusper-Schnitte an sauer-scharf Sauce</name>
          <note>gelb (Ampel)</note>
          <note>vegan</note>
          <note>Antioxidationsmittel</note>
          <note>Sellerie</note>
          <note>Soja</note>
          <note>Senf</note>
          <note>Schwefeldioxid und Sulfide</note>
          <note>Hefe</note>
          <note>Weizen</note>
          <price role="student">1.25</price>
          <price role="employee">2.50</price>
          <price role="other">2.75</price>
        </meal>
        <meal>
          <name>Kartoffel-Gemüse-Auflauf an Schnittlauchsauce</name>
          <note>grün (Ampel)</note>
          <note>vegetarisch</note>
          <note>Eier</note>
          <note>Sellerie</note>
          <note>Milch und Milchprodukte (inkl. Laktose)</note>
          <price role="student">1.35</price>
          <price role="employee">2.70</price>
          <price role="other">2.95</price>
        </meal>
      </category>
      <category name="Beilagen">
        <meal>
          <name>Currygemüse</name>
          <note>grün (Ampel)</note>
          <note>vegan</note>
          <note>Soja</note>
          <note>Sesam</note>
          <price role="student">0.55</price>
          <price role="employee">1.10</price>
          <price role="other">1.20</price>
        </meal>
        <meal>
          <name>Basmatireis</name>
          <note>gelb (Ampel)</note>
          <note>vegan</note>
          <price role="student">0.55</price>
          <price role="employee">1.10</price>
          <price role="other">1.20</price>
        </meal>
        <meal>
          <name>Zitronen-Gemüse-Sauce</name>
          <note>gelb (Ampel)</note>
          <note>vegetarisch</note>
          <note>Sellerie</note>
          <note>Milch und Milchprodukte (inkl. Laktose)</note>
          <price role="student">0.25</price>
          <price role="employee">0.50</price>
          <price role="other">0.55</price>
        </meal>
        <meal>
          <name>Sauer-scharf Sauce</name>
          <note>grün (Ampel)</note>
          <note>vegan</note>
          <note>Antioxidationsmittel</note>
          <note>Soja</note>
          <note>Schwefeldioxid und Sulfide</note>
          <price role="student">0.25</price>
          <price role="employee">0.50</price>
          <price role="other">0.55</price>
        </meal>
      </category>
    </day>
    <day date="2018-04-26">
      <category name="Salate">
        <meal>
          <name>Große Salatschale</name>
          <note>grün (Ampel)</note>
          <note>vegan</note>
          <note>Süßungsmittel</note>
          <note>Sellerie</note>
          <price role="student">1.65</price>
          <price role="employee">3.30</price>
          <price role="other">3.65</price>
        </meal>
        <meal>
          <name>Kleine Salatschale</name>
          <note>grün (Ampel)</note>
          <note>vegan</note>
          <note>Süßungsmittel</note>
          <note>Sellerie</note>
          <price role="student">0.60</price>
          <price role="employee">1.20</price>
          <price role="other">1.30</price>
        </meal>
      </category>
      <category name="Aktionen">
        <meal>
          <name>Quarkbecher mit Früchten</name>
          <note>gelb (Ampel)</note>
          <note>vegetarisch</note>
          <note>Antioxidationsmittel</note>
          <note>Milch und Milchprodukte (inkl. Laktose)</note>
          <price role="student">1.45</price>
          <price role="employee">1.45</price>
          <price role="other">1.45</price>
        </meal>
        <meal>
          <name>Joghurtbecher mit Früchten</name>
          <note>grün (Ampel)</note>
          <note>vegetarisch</note>
          <note>Antioxidationsmittel</note>
          <note>Milch und Milchprodukte (inkl. Laktose)</note>
          <price role="student">1.45</price>
          <price role="employee">1.45</price>
          <price role="other">1.45</price>
        </meal>
      </category>
      <category name="Essen">
        <meal>
          <name>Pfannenfrisches Hähnchengyros mit Weißkohl, Zwiebeln und Paprika Tzatziki</name>
          <note>grün (Ampel)</note>
          <note>Antioxidationsmittel</note>
          <note>Eier</note>
          <note>Sellerie</note>
          <note>Milch und Milchprodukte (inkl. Laktose)</note>
          <price role="student">1.95</price>
          <price role="employee">3.90</price>
          <price role="other">4.30</price>
        </meal>
        <meal>
          <name>Eine gebratene Lammfrikadelle an Rosmarinsauce</name>
          <note>rot (Ampel)</note>
          <note>mit zum Teil fein zerkleinertem Fleischanteil</note>
          <note>Eier</note>
          <note>Sellerie</note>
          <note>Senf</note>
          <note>Hefe</note>
          <note>Weizen</note>
          <price role="student">1.85</price>
          <price role="employee">3.70</price>
          <price role="other">4.05</price>
        </meal>
        <meal>
          <name>Spaghetti mit Getreidebolognese, frischen Karotten, Sellerie und Tomaten</name>
          <note>gelb (Ampel)</note>
          <note>vegan</note>
          <note>Klimaessen</note>
          <note>Sellerie</note>
          <note>Weizen</note>
          <note>Roggen</note>
          <note>Gerste</note>
          <note>Hafer</note>
          <note>Dinkel</note>
          <price role="student">1.75</price>
          <price role="employee">3.50</price>
          <price role="other">3.85</price>
        </meal>
        <meal>
          <name>Karotteneintopf</name>
          <note>grün (Ampel)</note>
          <note>vegan</note>
          <price role="student">1.35</price>
          <price role="employee">2.70</price>
          <price role="other">2.95</price>
        </meal>
        <meal>
          <name>Tiroler Kaiserschmarrn mit Rosinen und Apfelkompott</name>
          <note>gelb (Ampel)</note>
          <note>vegetarisch</note>
          <note>Antioxidationsmittel</note>
          <note>Eier</note>
          <note>Erdnüsse</note>
          <note>Milch und Milchprodukte (inkl. Laktose)</note>
          <note>Weizen</note>
          <price role="student">1.35</price>
          <price role="employee">2.70</price>
          <price role="other">2.95</price>
        </meal>
      </category>
      <category name="Beilagen">
        <meal>
          <name>Ratatouille</name>
          <note>grün (Ampel)</note>
          <note>vegan</note>
          <note>Sellerie</note>
          <price role="student">0.55</price>
          <price role="employee">1.10</price>
          <price role="other">1.20</price>
        </meal>
        <meal>
          <name>Pommes frites</name>
          <note>gelb (Ampel)</note>
          <note>vegan</note>
          <price role="student">0.70</price>
          <price role="employee">1.40</price>
          <price role="other">1.55</price>
        </meal>
        <meal>
          <name>Olivenreis</name>
          <note>gelb (Ampel)</note>
          <note>vegan</note>
          <price role="student">0.55</price>
          <price role="employee">1.10</price>
          <price role="other">1.20</price>
        </meal>
        <meal>
          <name>Rosmarinsauce</name>
          <note>gelb (Ampel)</note>
          <note>Senf</note>
          <price role="student">0.25</price>
          <price role="employee">0.50</price>
          <price role="other">0.55</price>
        </meal>
      </category>
    </day>
    <day date="2018-04-27">
      <category name="Salate">
        <meal>
          <name>Große Salatschale</name>
          <note>grün (Ampel)</note>
          <note>vegan</note>
          <note>Süßungsmittel</note>
          <note>Sellerie</note>
          <price role="student">1.65</price>
          <price role="employee">3.30</price>
          <price role="other">3.65</price>
        </meal>
        <meal>
          <name>Kleine Salatschale</name>
          <note>grün (Ampel)</note>
          <note>vegan</note>
          <note>Süßungsmittel</note>
          <note>Sellerie</note>
          <price role="student">0.60</price>
          <price role="employee">1.20</price>
          <price role="other">1.30</price>
        </meal>
      </category>
      <category name="Aktionen">
        <meal>
          <name>Quarkbecher mit Früchten</name>
          <note>gelb (Ampel)</note>
          <note>vegetarisch</note>
          <note>Antioxidationsmittel</note>
          <note>Milch und Milchprodukte (inkl. Laktose)</note>
          <price role="student">1.45</price>
          <price role="employee">1.45</price>
          <price role="other">1.45</price>
        </meal>
        <meal>
          <name>Joghurtbecher mit Früchten</name>
          <note>grün (Ampel)</note>
          <note>vegetarisch</note>
          <note>Antioxidationsmittel</note>
          <note>Milch und Milchprodukte (inkl. Laktose)</note>
          <price role="student">1.45</price>
          <price role="employee">1.45</price>
          <price role="other">1.45</price>
        </meal>
      </category>
      <category name="Essen">
        <meal>
          <name>Kichererbsenragout mit Kartoffeln, Kreuzkümmel und Koriander</name>
          <note>grün (Ampel)</note>
          <note>vegan</note>
          <note>Klimaessen</note>
          <note>Antioxidationsmittel</note>
          <note>Soja</note>
          <price role="student">1.75</price>
          <price role="employee">3.50</price>
          <price role="other">3.85</price>
        </meal>
        <meal>
          <name>Ofenfrische Putenbrust an Preiselbeerjus</name>
          <note>gelb (Ampel)</note>
          <price role="student">1.65</price>
          <price role="employee">3.30</price>
          <price role="other">3.65</price>
        </meal>
        <meal>
          <name>Ein gebackenes Seelachsfilet in Knusperpanade an Zitronen-Gemüse-Sauce</name>
          <note>gelb (Ampel)</note>
          <note>MSC</note>
          <note>Sellerie</note>
          <note>Milch und Milchprodukte (inkl. Laktose)</note>
          <note>Hefe</note>
          <note>Weizen</note>
          <price role="student">1.55</price>
          <price role="employee">3.10</price>
          <price role="other">3.40</price>
        </meal>
        <meal>
          <name>Glasnudelpfanne mit Austernpilzen</name>
          <note>grün (Ampel)</note>
          <note>vegan</note>
          <note>konserviert</note>
          <note>Soja</note>
          <note>Schwefeldioxid und Sulfide</note>
          <price role="student">1.35</price>
          <price role="employee">2.70</price>
          <price role="other">2.95</price>
        </meal>
      </category>
      <category name="Beilagen">
        <meal>
          <name>Balkangemüse</name>
          <note>grün (Ampel)</note>
          <note>vegan</note>
          <note>Sellerie</note>
          <price role="student">0.55</price>
          <price role="employee">1.10</price>
          <price role="other">1.20</price>
        </meal>
        <meal>
          <name>Stampfkartoffeln</name>
          <note>grün (Ampel)</note>
          <note>vegan</note>
          <price role="student">0.70</price>
          <price role="employee">1.40</price>
          <price role="other">1.55</price>
        </meal>
        <meal>
          <name>Paprikareis</name>
          <note>grün (Ampel)</note>
          <note>vegan</note>
          <price role="student">0.55</price>
          <price role="employee">1.10</price>
          <price role="other">1.20</price>
        </meal>
        <meal>
          <name>Rosmarinsauce</name>
          <note>gelb (Ampel)</note>
          <note>Senf</note>
          <price role="student">0.25</price>
          <price role="employee">0.50</price>
          <price role="other">0.55</price>
        </meal>
        <meal>
          <name>Preiselbeerjus</name>
          <note>gelb (Ampel)</note>
          <price role="student">0.25</price>
          <price role="employee">0.50</price>
          <price role="other">0.55</price>
        </meal>
      </category>
    </day>
    <day date="2018-04-28">
      <closed></closed>
    </day>
    <day date="2018-04-29">
      <closed></closed>
    </day>
    <day date="2018-04-30">
      <category name="Salate">
        <meal>
          <name>Große Salatschale</name>
          <note>grün (Ampel)</note>
          <note>vegan</note>
          <note>Süßungsmittel</note>
          <note>Sellerie</note>
          <price role="student">1.65</price>
          <price role="employee">3.30</price>
          <price role="other">3.65</price>
        </meal>
        <meal>
          <name>Kleine Salatschale</name>
          <note>grün (Ampel)</note>
          <note>vegan</note>
          <note>Süßungsmittel</note>
          <note>Sellerie</note>
          <price role="student">0.60</price>
          <price role="employee">1.20</price>
          <price role="other">1.30</price>
        </meal>
      </category>
      <category name="Beilagen">
        <meal>
          <name>Koriander-Chili-Dip</name>
          <note>rot (Ampel)</note>
          <note>vegan</note>
          <note>Süßungsmittel</note>
          <note>Soja</note>
          <note>Sesam</note>
          <price role="student">0.25</price>
          <price role="employee">0.50</price>
          <price role="other">0.55</price>
        </meal>
        <meal>
          <name>Waldpilz-Kräuter-Sauce</name>
          <note>gelb (Ampel)</note>
          <price role="student">0.25</price>
          <price role="employee">0.50</price>
          <price role="other">0.55</price>
        </meal>
      </category>
    </day>
    <day date="2018-05-01">
      <closed></closed>
    </day>
    <day date="2018-05-02">
      <category name="Salate">
        <meal>
          <name>Große Salatschale</name>
          <note>grün (Ampel)</note>
          <note>vegan</note>
          <note>Süßungsmittel</note>
          <note>Sellerie</note>
          <price role="student">1.65</price>
          <price role="employee">3.30</price>
          <price role="other">3.65</price>
        </meal>
        <meal>
          <name>Kleine Salatschale</name>
          <note>grün (Ampel)</note>
          <note>vegan</note>
          <note>Süßungsmittel</note>
          <note>Sellerie</note>
          <price role="student">0.60</price>
          <price role="employee">1.20</price>
          <price role="other">1.30</price>
        </meal>
      </category>
      <category name="Aktionen">
        <meal>
          <name>Joghurtbecher mit Früchten</name>
          <note>grün (Ampel)</note>
          <note>vegetarisch</note>
          <note>Antioxidationsmittel</note>
          <note>Milch und Milchprodukte (inkl. Laktose)</note>
          <price role="student">1.15</price>
          <price role="employee">1.15</price>
          <price role="other">1.15</price>
        </meal>
        <meal>
          <name>Quarkbecher mit Früchten</name>
          <note>gelb (Ampel)</note>
          <note>vegetarisch</note>
          <note>Antioxidationsmittel</note>
          <note>Milch und Milchprodukte (inkl. Laktose)</note>
          <price role="student">1.15</price>
          <price role="employee">1.15</price>
          <price role="other">1.15</price>
        </meal>
        <meal>
          <name>Obstsalat</name>
          <note>grün (Ampel)</note>
          <note>vegan</note>
          <note>Antioxidationsmittel</note>
          <price role="student">1.15</price>
          <price role="employee">1.15</price>
          <price role="other">1.15</price>
        </meal>
      </category>
      <category name="Essen">
        <meal>
          <name>Vegetarisch gefüllte Zucchini mit Mozzarella überbacken an Rucolasauce</name>
          <note>gelb (Ampel)</note>
          <note>vegetarisch</note>
          <note>konserviert</note>
          <note>Sellerie</note>
          <note>Milch und Milchprodukte (inkl. Laktose)</note>
          <price role="student">1.65</price>
          <price role="employee">3.30</price>
          <price role="other">3.65</price>
        </meal>
        <meal>
          <name>Ein Schweineschnitzel Cordon bleu an Bratensauce</name>
          <note>rot (Ampel)</note>
          <note>Schweinefleisch bzw. mit Gelatine vom Schwein</note>
          <note>konserviert</note>
          <note>Antioxidationsmittel</note>
          <note>Farbstoff</note>
          <note>Senf</note>
          <note>Milch und Milchprodukte (inkl. Laktose)</note>
          <note>Hefe</note>
          <note>Weizen</note>
          <price role="student">1.55</price>
          <price role="employee">3.10</price>
          <price role="other">3.40</price>
        </meal>
        <meal>
          <name>Vegane Reispfanne Paella an Tomatenragout</name>
          <note>grün (Ampel)</note>
          <note>vegan</note>
          <price role="student">1.35</price>
          <price role="employee">2.70</price>
          <price role="other">2.95</price>
        </meal>
      </category>
      <category name="Beilagen">
        <meal>
          <name>Brokkoli</name>
          <note>grün (Ampel)</note>
          <note>vegan</note>
          <price role="student">0.55</price>
          <price role="employee">1.10</price>
          <price role="other">1.20</price>
        </meal>
        <meal>
          <name>Stampfkartoffeln</name>
          <note>grün (Ampel)</note>
          <note>vegan</note>
          <price role="student">0.70</price>
          <price role="employee">1.40</price>
          <price role="other">1.55</price>
        </meal>
        <meal>
          <name>Zucchinireis</name>
          <note>gelb (Ampel)</note>
          <note>vegan</note>
          <price role="student">0.55</price>
          <price role="employee">1.10</price>
          <price role="other">1.20</price>
        </meal>
        <meal>
          <name>Rucolasauce</name>
          <note>gelb (Ampel)</note>
          <note>vegetarisch</note>
          <note>Sellerie</note>
          <note>Milch und Milchprodukte (inkl. Laktose)</note>
          <price role="student">0.25</price>
          <price role="employee">0.50</price>
          <price role="other">0.55</price>
        </meal>
        <meal>
          <name>Bratensauce</name>
          <note>gelb (Ampel)</note>
          <note>Senf</note>
          <price role="student">0.25</price>
          <price role="employee">0.50</price>
          <price role="other">0.55</price>
        </meal>
      </category>
    </day>
    <day date="2018-05-03">
      <category name="Salate">
        <meal>
          <name>Große Salatschale</name>
          <note>grün (Ampel)</note>
          <note>vegan</note>
          <note>Süßungsmittel</note>
          <note>Sellerie</note>
          <price role="student">1.65</price>
          <price role="employee">3.30</price>
          <price role="other">3.65</price>
        </meal>
        <meal>
          <name>Kleine Salatschale</name>
          <note>grün (Ampel)</note>
          <note>vegan</note>
          <note>Süßungsmittel</note>
          <note>Sellerie</note>
          <price role="student">0.60</price>
          <price role="employee">1.20</price>
          <price role="other">1.30</price>
        </meal>
      </category>
      <category name="Aktionen">
        <meal>
          <name>Joghurtbecher mit Früchten</name>
          <note>grün (Ampel)</note>
          <note>vegetarisch</note>
          <note>Antioxidationsmittel</note>
          <note>Milch und Milchprodukte (inkl. Laktose)</note>
          <price role="student">1.15</price>
          <price role="employee">1.15</price>
          <price role="other">1.15</price>
        </meal>
        <meal>
          <name>Quarkbecher mit Früchten</name>
          <note>gelb (Ampel)</note>
          <note>vegetarisch</note>
          <note>Antioxidationsmittel</note>
          <note>Milch und Milchprodukte (inkl. Laktose)</note>
          <price role="student">1.15</price>
          <price role="employee">1.15</price>
          <price role="other">1.15</price>
        </meal>
        <meal>
          <name>Obstsalat</name>
          <note>grün (Ampel)</note>
          <note>vegan</note>
          <note>Antioxidationsmittel</note>
          <price role="student">1.15</price>
          <price role="employee">1.15</price>
          <price role="other">1.15</price>
        </meal>
      </category>
      <category name="Essen">
        <meal>
          <name>Zwei Spinat-Dinkel-Medaillons an Bärlauchsauce</name>
          <note>rot (Ampel)</note>
          <note>vegetarisch</note>
          <note>Eier</note>
          <note>Sellerie</note>
          <note>Milch und Milchprodukte (inkl. Laktose)</note>
          <note>Weizen</note>
          <note>Dinkel</note>
          <price role="student">1.65</price>
          <price role="employee">3.30</price>
          <price role="other">3.65</price>
        </meal>
        <meal>
          <name>Eine gebackene Hähnchenbrust Florentiner Art an Geflügeljus</name>
          <note>rot (Ampel)</note>
          <note>Milch und Milchprodukte (inkl. Laktose)</note>
          <note>Hefe</note>
          <note>Weizen</note>
          <price role="student">1.55</price>
          <price role="employee">3.10</price>
          <price role="other">3.40</price>
        </meal>
        <meal>
          <name>Kartoffel-Gemüse-Pfanne mit Schluppen</name>
          <note>grün (Ampel)</note>
          <note>vegan</note>
          <price role="student">1.35</price>
          <price role="employee">2.70</price>
          <price role="other">2.95</price>
        </meal>
      </category>
      <category name="Beilagen">
        <meal>
          <name>Geschmorte Auberginen mit Tomaten</name>
          <note>grün (Ampel)</note>
          <note>vegan</note>
          <price role="student">0.55</price>
          <price role="employee">1.10</price>
          <price role="other">1.20</price>
        </meal>
        <meal>
          <name>Rosmarinkartoffeln</name>
          <note>grün (Ampel)</note>
          <note>vegan</note>
          <price role="student">0.70</price>
          <price role="employee">1.40</price>
          <price role="other">1.55</price>
        </meal>
        <meal>
          <name>Parboiledreis</name>
          <note>gelb (Ampel)</note>
          <note>vegan</note>
          <price role="student">0.55</price>
          <price role="employee">1.10</price>
          <price role="other">1.20</price>
        </meal>
        <meal>
          <name>Bärlauchsauce</name>
          <note>rot (Ampel)</note>
          <note>vegetarisch</note>
          <note>Milch und Milchprodukte (inkl. Laktose)</note>
          <price role="student">0.25</price>
          <price role="employee">0.50</price>
          <price role="other">0.55</price>
        </meal>
        <meal>
          <name>Geflügeljus</name>
          <note>gelb (Ampel)</note>
          <price role="student">0.25</price>
          <price role="employee">0.50</price>
          <price role="other">0.55</price>
        </meal>
      </category>
    </day>
    <day date="2018-05-04">
      <category name="Salate">
        <meal>
          <name>Große Salatschale</name>
          <note>grün (Ampel)</note>
          <note>vegan</note>
          <note>Süßungsmittel</note>
          <note>Sellerie</note>
          <price role="student">1.65</price>
          <price role="employee">3.30</price>
          <price role="other">3.65</price>
        </meal>
        <meal>
          <name>Kleine Salatschale</name>
          <note>grün (Ampel)</note>
          <note>vegan</note>
          <note>Süßungsmittel</note>
          <note>Sellerie</note>
          <price role="student">0.60</price>
          <price role="employee">1.20</price>
          <price role="other">1.30</price>
        </meal>
      </category>
      <category name="Aktionen">
        <meal>
          <name>Spaghetti mit Zucchini-Tomaten-Ragout und frischem Basilikum</name>
          <note>grün (Ampel)</note>
          <note>vegan</note>
          <note>Sellerie</note>
          <note>Weizen</note>
          <price role="student">2.95</price>
          <price role="employee">2.95</price>
          <price role="other">2.95</price>
        </meal>
        <meal>
          <name>Quarkbecher mit Früchten</name>
          <note>gelb (Ampel)</note>
          <note>vegetarisch</note>
          <note>Antioxidationsmittel</note>
          <note>Milch und Milchprodukte (inkl. Laktose)</note>
          <price role="student">1.15</price>
          <price role="employee">1.15</price>
          <price role="other">1.15</price>
        </meal>
        <meal>
          <name>Obstsalat</name>
          <note>grün (Ampel)</note>
          <note>vegan</note>
          <note>Antioxidationsmittel</note>
          <price role="student">1.15</price>
          <price role="employee">1.15</price>
          <price role="other">1.15</price>
        </meal>
        <meal>
          <name>Joghurtbecher mit Früchten</name>
          <note>grün (Ampel)</note>
          <note>vegetarisch</note>
          <note>Antioxidationsmittel</note>
          <note>Milch und Milchprodukte (inkl. Laktose)</note>
          <price role="student">1.15</price>
          <price role="employee">1.15</price>
          <price role="other">1.15</price>
        </meal>
      </category>
      <category name="Essen">
        <meal>
          <name>Fünf Cevapcici vom Rind an Barbecuesauce</name>
          <note>gelb (Ampel)</note>
          <note>Süßungsmittel</note>
          <note>mit zum Teil fein zerkleinertem Fleischanteil</note>
          <note>Senf</note>
          <note>Hefe</note>
          <note>Weizen</note>
          <price role="student">1.65</price>
          <price role="employee">3.30</price>
          <price role="other">3.65</price>
        </meal>
        <meal>
          <name>Gebackenes Seelachsfilet in Knusperkernpanade mit Estragonrahmsauce</name>
          <note>rot (Ampel)</note>
          <note>MSC</note>
          <note>Antioxidationsmittel</note>
          <note>Fisch</note>
          <note>Sellerie</note>
          <note>Milch und Milchprodukte (inkl. Laktose)</note>
          <note>Schwefeldioxid und Sulfide</note>
          <note>Hefe</note>
          <note>Weizen</note>
          <price role="student">1.55</price>
          <price role="employee">3.10</price>
          <price role="other">3.40</price>
        </meal>
        <meal>
          <name>Thailändischer Gemüsetopf mit Ingwer, Kokosmilch und Huhn</name>
          <note>grün (Ampel)</note>
          <note>Antioxidationsmittel</note>
          <note>Eier</note>
          <note>Soja</note>
          <note>Milch und Milchprodukte (inkl. Laktose)</note>
          <price role="student">1.35</price>
          <price role="employee">2.70</price>
          <price role="other">2.95</price>
        </meal>
      </category>
      <category name="Beilagen">
        <meal>
          <name>Romanesco</name>
          <note>grün (Ampel)</note>
          <note>vegan</note>
          <price role="student">0.55</price>
          <price role="employee">1.10</price>
          <price role="other">1.20</price>
        </meal>
        <meal>
          <name>Süßkartoffelpüree</name>
          <note>grün (Ampel)</note>
          <note>vegetarisch</note>
          <note>Milch und Milchprodukte (inkl. Laktose)</note>
          <price role="student">0.70</price>
          <price role="employee">1.40</price>
          <price role="other">1.55</price>
        </meal>
        <meal>
          <name>Spiralnudeln</name>
          <note>gelb (Ampel)</note>
          <note>vegan</note>
          <note>Weizen</note>
          <price role="student">0.55</price>
          <price role="employee">1.10</price>
          <price role="other">1.20</price>
        </meal>
        <meal>
          <name>Barbecuesauce</name>
          <note>gelb (Ampel)</note>
          <note>Süßungsmittel</note>
          <note>Senf</note>
          <price role="student">0.25</price>
          <price role="employee">0.50</price>
          <price role="other">0.55</price>
        </meal>
        <meal>
          <name>Estragonrahmsauce</name>
          <note>rot (Ampel)</note>
          <note>Antioxidationsmittel</note>
          <note>Fisch</note>
          <note>Sellerie</note>
          <note>Milch und Milchprodukte (inkl. Laktose)</note>
          <note>Schwefeldioxid und Sulfide</note>
          <note>Weizen</note>
          <price role="student">0.25</price>
          <price role="employee">0.50</price>
          <price role="other">0.55</price>
        </meal>
      </category>
    </day>
    <day date="2018-05-05">
      <closed></closed>
    </day>
    <day date="2018-05-06">
      <closed></closed>
    </day>
    <day date="2018-05-07">
      <category name="Salate">
        <meal>
          <name>Große Salatschale</name>
          <note>grün (Ampel)</note>
          <note>vegan</note>
          <note>Süßungsmittel</note>
          <note>Sellerie</note>
          <price role="student">1.65</price>
          <price role="employee">3.30</price>
          <price role="other">3.65</price>
        </meal>
        <meal>
          <name>Kleine Salatschale</name>
          <note>grün (Ampel)</note>
          <note>vegan</note>
          <note>Süßungsmittel</note>
          <note>Sellerie</note>
          <price role="student">0.60</price>
          <price role="employee">1.20</price>
          <price role="other">1.30</price>
        </meal>
      </category>
      <category name="Essen">
        <meal>
          <name>Eine Hähnchenbrust mit Pesto überbacken an Geflügelrahmsauce</name>
          <note>rot (Ampel)</note>
          <note>Milch und Milchprodukte (inkl. Laktose)</note>
          <note>Hefe</note>
          <note>Weizen</note>
          <price role="student">1.95</price>
          <price role="employee">3.90</price>
          <price role="other">4.30</price>
        </meal>
        <meal>
          <name>Zwei Fleischklopse Königsberger Art in Kapernsauce</name>
          <note>gelb (Ampel)</note>
          <note>Schweinefleisch bzw. mit Gelatine vom Schwein</note>
          <note>Antioxidationsmittel</note>
          <note>mit zum Teil fein zerkleinertem Fleischanteil</note>
          <note>Eier</note>
          <note>Milch und Milchprodukte (inkl. Laktose)</note>
          <price role="student">1.25</price>
          <price role="employee">2.50</price>
          <price role="other">2.75</price>
        </meal>
        <meal>
          <name>Italienisches Tomaten-Basilikum-Risotto an Schnittlauchsauce</name>
          <note>gelb (Ampel)</note>
          <note>konserviert</note>
          <note>Eier</note>
          <note>Milch und Milchprodukte (inkl. Laktose)</note>
          <price role="student">1.35</price>
          <price role="employee">2.70</price>
          <price role="other">2.95</price>
        </meal>
      </category>
    </day>
    <day date="2018-05-08">
      <category name="Salate">
        <meal>
          <name>Große Salatschale</name>
          <note>grün (Ampel)</note>
          <note>vegan</note>
          <note>Süßungsmittel</note>
          <note>Sellerie</note>
          <price role="student">1.65</price>
          <price role="employee">3.30</price>
          <price role="other">3.65</price>
        </meal>
        <meal>
          <name>Kleine Salatschale</name>
          <note>grün (Ampel)</note>
          <note>vegan</note>
          <note>Süßungsmittel</note>
          <note>Sellerie</note>
          <price role="student">0.60</price>
          <price role="employee">1.20</price>
          <price role="other">1.30</price>
        </meal>
      </category>
      <category name="Essen">
        <meal>
          <name>Bulgur-Gemüse-Medaillon an Kräutersauce</name>
          <note>rot (Ampel)</note>
          <note>vegetarisch</note>
          <note>Farbstoff</note>
          <note>Eier</note>
          <note>Milch und Milchprodukte (inkl. Laktose)</note>
          <note>Hefe</note>
          <note>Weizen</note>
          <price role="student">1.65</price>
          <price role="employee">3.30</price>
          <price role="other">3.65</price>
        </meal>
        <meal>
          <name>Rindergulasch nach ungarischer Art</name>
          <note>gelb (Ampel)</note>
          <note>Antioxidationsmittel</note>
          <price role="student">1.55</price>
          <price role="employee">3.10</price>
          <price role="other">3.40</price>
        </meal>
        <meal>
          <name>Rote Linsen-Süßkartoffel-Topf mit Gemüse und frischem Ingwer</name>
          <note>grün (Ampel)</note>
          <note>vegan</note>
          <note>Antioxidationsmittel</note>
          <note>Sellerie</note>
          <note>Soja</note>
          <note>Kaschunuss</note>
          <price role="student">1.35</price>
          <price role="employee">2.70</price>
          <price role="other">2.95</price>
        </meal>
      </category>
    </day>
    <day date="2018-05-09">
      <category name="Salate">
        <meal>
          <name>Große Salatschale</name>
          <note>grün (Ampel)</note>
          <note>vegan</note>
          <note>Süßungsmittel</note>
          <note>Sellerie</note>
          <price role="student">1.65</price>
          <price role="employee">3.30</price>
          <price role="other">3.65</price>
        </meal>
        <meal>
          <name>Kleine Salatschale</name>
          <note>grün (Ampel)</note>
          <note>vegan</note>
          <note>Süßungsmittel</note>
          <note>Sellerie</note>
          <price role="student">0.60</price>
          <price role="employee">1.20</price>
          <price role="other">1.30</price>
        </meal>
      </category>
      <category name="Essen">
        <meal>
          <name>Ein Seelachsfilet mit Tomaten und Mozzarella überbacken an Zitronen-Gemüse-Sauce</name>
          <note>gelb (Ampel)</note>
          <note>MSC</note>
          <note>Sellerie</note>
          <note>Soja</note>
          <note>Milch und Milchprodukte (inkl. Laktose)</note>
          <note>Hefe</note>
          <note>Weizen</note>
          <price role="student">2.45</price>
          <price role="employee">4.90</price>
          <price role="other">5.40</price>
        </meal>
        <meal>
          <name>Zwei gebackene Kartoffeltaschen mit Frischkäsefüllung an Quarkdip</name>
          <note>gelb (Ampel)</note>
          <note>vegetarisch</note>
          <note>Milch und Milchprodukte (inkl. Laktose)</note>
          <price role="student">1.25</price>
          <price role="employee">2.50</price>
          <price role="other">2.75</price>
        </meal>
        <meal>
          <name>Reispfanne mit Rindfleisch, Mais, Paprika und Tomaten</name>
          <note>grün (Ampel)</note>
          <note>mit zum Teil fein zerkleinertem Fleischanteil</note>
          <price role="student">1.35</price>
          <price role="employee">2.70</price>
          <price role="other">2.95</price>
        </meal>
      </category>
    </day>
  </canteen>
</openmensa>
