<?xml version="1.0" encoding="UTF-8"?>
<openmensa version="2.1"
           xmlns="http://openmensa.org/open-mensa-v2"
           xmlns:xsi="http://www.w3.org/2001/XMLSchema-instance"
           xsi:schemaLocation="http://openmensa.org/open-mensa-v2 http://openmensa.org/open-mensa-v2.xsd">
  <canteen>
    <day date="2018-07-23">
      <category name="Salate">
        <meal>
          <name>Kleine Salatschale</name>
          <note>grün (Ampel)</note>
          <note>vegan</note>
          <note>Süßungsmittel</note>
          <note>Sellerie</note>
          <price role="student">1.20</price>
          <price role="employee">1.20</price>
          <price role="other">1.20</price>
        </meal>
      </category>
      <category name="Suppen">
        <meal>
          <name>Waldpilzcremesuppe mit Rosmarin</name>
          <note>gelb (Ampel)</note>
          <note>vegetarisch</note>
          <note>Sellerie</note>
          <note>Milch und Milchprodukte (inkl. Laktose)</note>
          <price role="student">1.95</price>
          <price role="employee">1.95</price>
          <price role="other">2.45</price>
        </meal>
      </category>
      <category name="Aktionen">
        <meal>
          <name>Kalbsgeschnetzeltes Zürcher Art mit Kartoffelrösti</name>
          <note>gelb (Ampel)</note>
          <note>Antioxidationsmittel</note>
          <note>Weizen</note>
          <note>Eier</note>
          <note>Milch und Milchprodukte (inkl. Laktose)</note>
          <price role="student">5.95</price>
          <price role="employee">5.95</price>
          <price role="other">6.45</price>
        </meal>
        <meal>
          <name>Fettuccine mit Tomatensauce, Weichkäse und frischem Basilikum</name>
          <note>grün (Ampel)</note>
          <note>vegetarisch</note>
          <note>geschwärzt</note>
          <note>Weizen</note>
          <note>Eier</note>
          <note>Sellerie</note>
          <note>Milch und Milchprodukte (inkl. Laktose)</note>
          <price role="student">3.95</price>
          <price role="employee">3.95</price>
          <price role="other">4.45</price>
        </meal>
        <meal>
          <name>Gebratenes Wildlachsfilet an Fischrahmsauce mit Gemüse Julienne Tomatenreis</name>
          <note>gelb (Ampel)</note>
          <note>MSC</note>
          <note>Antioxidationsmittel</note>
          <note>Weizen</note>
          <note>Fisch</note>
          <note>Sellerie</note>
          <note>Milch und Milchprodukte (inkl. Laktose)</note>
          <note>Schwefeldioxid und Sulfide</note>
          <price role="student">4.95</price>
          <price role="employee">4.95</price>
          <price role="other">5.45</price>
        </meal>
      </category>
    </day>
    <day date="2018-07-24">
      <category name="Salate">
        <meal>
          <name>Kleine Salatschale</name>
          <note>grün (Ampel)</note>
          <note>vegan</note>
          <note>Süßungsmittel</note>
          <note>Sellerie</note>
          <price role="student">1.20</price>
          <price role="employee">1.20</price>
          <price role="other">1.20</price>
        </meal>
      </category>
      <category name="Suppen">
        <meal>
          <name>Scharfe indische Kichererbsensuppe</name>
          <note>gelb (Ampel)</note>
          <note>vegan</note>
          <price role="student">1.95</price>
          <price role="employee">1.95</price>
          <price role="other">2.45</price>
        </meal>
      </category>
      <category name="Aktionen">
        <meal>
          <name>Gebratener Tofu mit Wokgemüse, frischem Ingwer und gelbem Reis</name>
          <note>grün (Ampel)</note>
          <note>vegan</note>
          <note>Antioxidationsmittel</note>
          <note>Sellerie</note>
          <note>Soja</note>
          <note>Schwefeldioxid und Sulfide</note>
          <price role="student">3.95</price>
          <price role="employee">3.95</price>
          <price role="other">4.45</price>
        </meal>
        <meal>
          <name>Putencurry mit asiatischem Gemüse und Kokosmilch Jasminreis Salat</name>
          <note>gelb (Ampel)</note>
          <note>Soja</note>
          <note>Milch und Milchprodukte (inkl. Laktose)</note>
          <price role="student">4.95</price>
          <price role="employee">4.95</price>
          <price role="other">5.45</price>
        </meal>
      </category>
      <category name="Essen">
        <meal>
          <name>Ein Schweineschnitzel Cordon bleu an Bratensauce Paprika-Zucchini-Gemüse Stampfkartoffeln</name>
          <note>gelb (Ampel)</note>
          <note>Schweinefleisch bzw. mit Gelatine vom Schwein</note>
          <note>konserviert</note>
          <note>Antioxidationsmittel</note>
          <note>Farbstoff</note>
          <note>Weizen</note>
          <note>Milch und Milchprodukte (inkl. Laktose)</note>
          <note>Hefe</note>
          <note>Senf</note>
          <price role="student">4.95</price>
          <price role="employee">4.95</price>
          <price role="other">5.45</price>
        </meal>
      </category>
    </day>
    <day date="2018-07-25">
      <category name="Salate">
        <meal>
          <name>Kleine Salatschale</name>
          <note>grün (Ampel)</note>
          <note>vegan</note>
          <note>Süßungsmittel</note>
          <note>Sellerie</note>
          <price role="student">1.20</price>
          <price role="employee">1.20</price>
          <price role="other">1.20</price>
        </meal>
      </category>
      <category name="Suppen">
        <meal>
          <name>Möhrensuppe mit Ingwer</name>
          <note>gelb (Ampel)</note>
          <note>vegetarisch</note>
          <note>Milch und Milchprodukte (inkl. Laktose)</note>
          <price role="student">1.95</price>
          <price role="employee">1.95</price>
          <price role="other">2.45</price>
        </meal>
      </category>
      <category name="Aktionen">
        <meal>
          <name>Seelachsburger mit Mango-Ingwer-Chutney im Mehrkornbrötchen,</name>
          <note>gelb (Ampel)</note>
          <note>MSC</note>
          <note>Farbstoff</note>
          <note>Weizen</note>
          <note>Roggen</note>
          <note>Gerste</note>
          <note>Hafer</note>
          <note>Milch und Milchprodukte (inkl. Laktose)</note>
          <note>Hefe</note>
          <price role="student">5.95</price>
          <price role="employee">5.95</price>
          <price role="other">6.45</price>
        </meal>
        <meal>
          <name>Rindergeschnetzeltes Stroganoff Art Parboiledreis Salat</name>
          <note>gelb (Ampel)</note>
          <note>konserviert</note>
          <note>Antioxidationsmittel</note>
          <note>Süßungsmittel</note>
          <note>Milch und Milchprodukte (inkl. Laktose)</note>
          <note>Senf</note>
          <price role="student">4.95</price>
          <price role="employee">4.95</price>
          <price role="other">5.45</price>
        </meal>
      </category>
      <category name="Essen">
        <meal>
          <name>Kartoffel-Gemüse-Pfanne mit Schluppen an Tahin-Yofudip mit frischen Kräutern</name>
          <note>grün (Ampel)</note>
          <note>vegan</note>
          <note>Antioxidationsmittel</note>
          <note>Soja</note>
          <note>Sesam</note>
          <price role="student">2.95</price>
          <price role="employee">2.95</price>
          <price role="other">3.45</price>
        </meal>
      </category>
    </day>
    <day date="2018-07-26">
      <category name="Salate">
        <meal>
          <name>Kleine Salatschale</name>
          <note>grün (Ampel)</note>
          <note>vegan</note>
          <note>Süßungsmittel</note>
          <note>Sellerie</note>
          <price role="student">1.20</price>
          <price role="employee">1.20</price>
          <price role="other">1.20</price>
        </meal>
      </category>
      <category name="Aktionen">
        <meal>
          <name>Bulgur-Gemüse-Burger mit Pommes frites und Salat</name>
          <note>gelb (Ampel)</note>
          <note>vegetarisch</note>
          <note>Farbstoff</note>
          <note>Süßungsmittel</note>
          <note>Weizen</note>
          <note>Eier</note>
          <note>Sellerie</note>
          <note>Soja</note>
          <note>Milch und Milchprodukte (inkl. Laktose)</note>
          <note>Sesam</note>
          <note>Hefe</note>
          <note>Senf</note>
          <price role="student">5.95</price>
          <price role="employee">5.95</price>
          <price role="other">6.45</price>
        </meal>
        <meal>
          <name>Fish &amp; Chips - Gebackenes Seelachsfilet mit Pommes frites,</name>
          <note>rot (Ampel)</note>
          <note>MSC</note>
          <note>Farbstoff</note>
          <note>Süßungsmittel</note>
          <note>Weizen</note>
          <note>Gerste</note>
          <note>Eier</note>
          <note>Sellerie</note>
          <note>Senf</note>
          <price role="student">4.95</price>
          <price role="employee">4.95</price>
          <price role="other">5.45</price>
        </meal>
        <meal>
          <name>Geflügelpfanne mit Ananas, Paprika, Kokosmilch auf Chinanudeln</name>
          <note>gelb (Ampel)</note>
          <note>Weizen</note>
          <note>Milch und Milchprodukte (inkl. Laktose)</note>
          <price role="student">4.95</price>
          <price role="employee">4.95</price>
          <price role="other">5.45</price>
        </meal>
      </category>
      <category name="Essen">
        <meal>
          <name>Rote Linsen-Süßkartoffel-Topf mit Gemüse und frischem Ingwer</name>
          <note>grün (Ampel)</note>
          <note>vegan</note>
          <note>Antioxidationsmittel</note>
          <note>Kaschunuss</note>
          <note>Sellerie</note>
          <note>Soja</note>
          <price role="student">2.95</price>
          <price role="employee">2.95</price>
          <price role="other">3.45</price>
        </meal>
      </category>
    </day>
    <day date="2018-07-27">
      <category name="Salate">
        <meal>
          <name>Kleine Salatschale</name>
          <note>grün (Ampel)</note>
          <note>vegan</note>
          <note>Süßungsmittel</note>
          <note>Sellerie</note>
          <price role="student">1.20</price>
          <price role="employee">1.20</price>
          <price role="other">1.20</price>
        </meal>
      </category>
      <category name="Suppen">
        <meal>
          <name>Brokkolicremesuppe</name>
          <note>grün (Ampel)</note>
          <note>vegetarisch</note>
          <note>Milch und Milchprodukte (inkl. Laktose)</note>
          <price role="student">1.95</price>
          <price role="employee">1.95</price>
          <price role="other">2.45</price>
        </meal>
      </category>
      <category name="Aktionen">
        <meal>
          <name>1/2 Grill Hähnchen mit Pommes frites und coleslaw</name>
          <note>rot (Ampel)</note>
          <note>Süßungsmittel</note>
          <note>Weizen</note>
          <note>Eier</note>
          <note>Sellerie</note>
          <note>Senf</note>
          <price role="student">6.95</price>
          <price role="employee">6.95</price>
          <price role="other">7.45</price>
        </meal>
      </category>
      <category name="Essen">
        <meal>
          <name>Eine vegetarische Frühlingsrolle an Koriander-Chili-Dip Chinagemüse Basmatireis</name>
          <note>gelb (Ampel)</note>
          <note>vegetarisch</note>
          <note>Antioxidationsmittel</note>
          <note>Süßungsmittel</note>
          <note>Weizen</note>
          <note>Eier</note>
          <note>Sellerie</note>
          <note>Soja</note>
          <note>Sesam</note>
          <note>Schwefeldioxid und Sulfide</note>
          <price role="student">3.95</price>
          <price role="employee">3.95</price>
          <price role="other">4.45</price>
        </meal>
      </category>
    </day>
    <day date="2018-07-28">
      <closed></closed>
    </day>
    <day date="2018-07-29">
      <closed></closed>
    </day>
    <day date="2018-07-30">
      <category name="Salate">
        <meal>
          <name>Kleine Salatschale</name>
          <note>grün (Ampel)</note>
          <note>vegan</note>
          <note>Süßungsmittel</note>
          <note>Sellerie</note>
          <price role="student">1.20</price>
          <price role="employee">1.20</price>
          <price role="other">1.20</price>
        </meal>
      </category>
      <category name="Aktionen">
        <meal>
          <name>Quinoa Chili Burger mit Pommes frites und Salat</name>
          <note>gelb (Ampel)</note>
          <note>vegetarisch</note>
          <note>Farbstoff</note>
          <note>Süßungsmittel</note>
          <note>Weizen</note>
          <note>Eier</note>
          <note>Sellerie</note>
          <note>Soja</note>
          <note>Milch und Milchprodukte (inkl. Laktose)</note>
          <note>Sesam</note>
          <note>Hefe</note>
          <note>Senf</note>
          <price role="student">5.95</price>
          <price role="employee">5.95</price>
          <price role="other">6.45</price>
        </meal>
        <meal>
          <name>Nasi Goreng - Indonesische Reis-Gemüse-Pfanne mit Schweinefleisch</name>
          <note>gelb (Ampel)</note>
          <note>Schweinefleisch bzw. mit Gelatine vom Schwein</note>
          <note>konserviert</note>
          <note>Soja</note>
          <note>Schwefeldioxid und Sulfide</note>
          <price role="student">3.95</price>
          <price role="employee">3.95</price>
          <price role="other">4.45</price>
        </meal>
      </category>
      <category name="Essen">
        <meal>
          <name>Rote Linsen-Süßkartoffel-Topf mit Gemüse und frischem Ingwer</name>
          <note>grün (Ampel)</note>
          <note>vegan</note>
          <note>Antioxidationsmittel</note>
          <note>Kaschunuss</note>
          <note>Sellerie</note>
          <note>Soja</note>
          <price role="student">2.95</price>
          <price role="employee">2.95</price>
          <price role="other">3.45</price>
        </meal>
        <meal>
          <name>Ein Seelachsfilet mit Tomaten und Mozzarella überbacken an Zitronen-Gemüse-Sauce Salzkartoffeln Gurkensalat mit Dill</name>
          <note>grün (Ampel)</note>
          <note>MSC</note>
          <note>Weizen</note>
          <note>Sellerie</note>
          <note>Soja</note>
          <note>Milch und Milchprodukte (inkl. Laktose)</note>
          <note>Hefe</note>
          <price role="student">5.95</price>
          <price role="employee">5.95</price>
          <price role="other">6.45</price>
        </meal>
      </category>
    </day>
    <day date="2018-07-31">
      <category name="Salate">
        <meal>
          <name>Kleine Salatschale</name>
          <note>grün (Ampel)</note>
          <note>vegan</note>
          <note>Süßungsmittel</note>
          <note>Sellerie</note>
          <price role="student">1.20</price>
          <price role="employee">1.20</price>
          <price role="other">1.20</price>
        </meal>
      </category>
      <category name="Suppen">
        <meal>
          <name>Süßkartoffelsuppe</name>
          <note>gelb (Ampel)</note>
          <note>vegetarisch</note>
          <note>Mandeln</note>
          <note>Milch und Milchprodukte (inkl. Laktose)</note>
          <price role="student">1.95</price>
          <price role="employee">1.95</price>
          <price role="other">2.45</price>
        </meal>
      </category>
      <category name="Aktionen">
        <meal>
          <name>Badische Schupfnudeln mit Spinatrahm und Tomatenwürfeln</name>
          <note>gelb (Ampel)</note>
          <note>vegetarisch</note>
          <note>Weizen</note>
          <note>Eier</note>
          <note>Milch und Milchprodukte (inkl. Laktose)</note>
          <price role="student">2.95</price>
          <price role="employee">2.95</price>
          <price role="other">3.45</price>
        </meal>
      </category>
      <category name="Essen">
        <meal>
          <name>Spaghetti mit Bologneser Sauce</name>
          <note>gelb (Ampel)</note>
          <note>konserviert</note>
          <note>mit zum Teil fein zerkleinertem Fleischanteil</note>
          <note>Weizen</note>
          <note>Eier</note>
          <note>Sellerie</note>
          <note>Milch und Milchprodukte (inkl. Laktose)</note>
          <price role="student">2.95</price>
          <price role="employee">2.95</price>
          <price role="other">3.45</price>
        </meal>
      </category>
    </day>
    <day date="2018-08-01">
      <category name="Salate">
        <meal>
          <name>Kleine Salatschale</name>
          <note>grün (Ampel)</note>
          <note>vegan</note>
          <note>Süßungsmittel</note>
          <note>Sellerie</note>
          <price role="student">1.20</price>
          <price role="employee">1.20</price>
          <price role="other">1.20</price>
        </meal>
      </category>
      <category name="Suppen">
        <meal>
          <name>Tomatencremesuppe mit frischem Basilkum</name>
          <note>gelb (Ampel)</note>
          <note>vegetarisch</note>
          <note>Farbstoff</note>
          <note>Milch und Milchprodukte (inkl. Laktose)</note>
          <note>Schwefeldioxid und Sulfide</note>
          <price role="student">1.95</price>
          <price role="employee">1.95</price>
          <price role="other">2.45</price>
        </meal>
      </category>
      <category name="Aktionen">
        <meal>
          <name>Thüringer Rostbrätl Bratkartoffeln Salat</name>
          <note>grün (Ampel)</note>
          <note>Schweinefleisch bzw. mit Gelatine vom Schwein</note>
          <note>Gerste</note>
          <note>Senf</note>
          <price role="student">4.95</price>
          <price role="employee">4.95</price>
          <price role="other">5.45</price>
        </meal>
        <meal>
          <name>Chinesische Gemüsepfanne mit frischem Ingwer auf Basmatireis</name>
          <note>grün (Ampel)</note>
          <note>vegan</note>
          <note>Sellerie</note>
          <note>Soja</note>
          <note>Schwefeldioxid und Sulfide</note>
          <price role="student">2.95</price>
          <price role="employee">2.95</price>
          <price role="other">3.45</price>
        </meal>
      </category>
      <category name="Essen">
        <meal>
          <name>Frankfurter Linseneintopf mit Wurzelgemüse und einem Wiener Würstchen</name>
          <note>grün (Ampel)</note>
          <note>Schweinefleisch bzw. mit Gelatine vom Schwein</note>
          <note>konserviert</note>
          <note>Antioxidationsmittel</note>
          <note>Sellerie</note>
          <note>Nitritpökelsalz</note>
          <note>Senf</note>
          <price role="student">2.95</price>
          <price role="employee">2.95</price>
          <price role="other">3.45</price>
        </meal>
        <meal>
          <name>Eine Scheibe Rheinischer Sauerbraten in Traubensauce Apfelrotkohl Zwei Kartoffelklöße</name>
          <note>grün (Ampel)</note>
          <note>Antioxidationsmittel</note>
          <note>Mandeln</note>
          <note>Sellerie</note>
          <note>Schwefeldioxid und Sulfide</note>
          <note>Senf</note>
          <price role="student">5.95</price>
          <price role="employee">5.95</price>
          <price role="other">6.45</price>
        </meal>
      </category>
    </day>
    <day date="2018-08-02">
      <category name="Salate">
        <meal>
          <name>Kleine Salatschale</name>
          <note>grün (Ampel)</note>
          <note>vegan</note>
          <note>Süßungsmittel</note>
          <note>Sellerie</note>
          <price role="student">1.20</price>
          <price role="employee">1.20</price>
          <price role="other">1.20</price>
        </meal>
      </category>
      <category name="Suppen">
        <meal>
          <name>Karotten-Ingwer-Suppe mit Chili</name>
          <note>gelb (Ampel)</note>
          <note>vegetarisch</note>
          <note>Milch und Milchprodukte (inkl. Laktose)</note>
          <price role="student">1.95</price>
          <price role="employee">1.95</price>
          <price role="other">2.45</price>
        </meal>
      </category>
      <category name="Aktionen">
        <meal>
          <name>Gebratenes Wildlachsfilet an Zitronen-Gemüse-Sauce Parboiledreis Salat</name>
          <note>gelb (Ampel)</note>
          <note>MSC</note>
          <note>Weizen</note>
          <note>Sellerie</note>
          <note>Milch und Milchprodukte (inkl. Laktose)</note>
          <price role="student">5.95</price>
          <price role="employee">5.95</price>
          <price role="other">6.45</price>
        </meal>
        <meal>
          <name>Ravioli Pomodoro mit Tomatensugo und Rucola</name>
          <note>grün (Ampel)</note>
          <note>vegan</note>
          <note>Weizen</note>
          <note>Sellerie</note>
          <note>Hefe</note>
          <price role="student">3.95</price>
          <price role="employee">3.95</price>
          <price role="other">4.45</price>
        </meal>
      </category>
      <category name="Essen">
        <meal>
          <name>Kichererbsen-Kartoffel-Pfanne mit frischem Koriander</name>
          <note>grün (Ampel)</note>
          <note>vegan</note>
          <note>Soja</note>
          <price role="student">2.95</price>
          <price role="employee">2.95</price>
          <price role="other">3.45</price>
        </meal>
        <meal>
          <name>Ein paniertes Rotbarschfilet an Kräuterremoulade Pfannengemüse Dillkartoffeln</name>
          <note>gelb (Ampel)</note>
          <note>MSC</note>
          <note>konserviert</note>
          <note>Süßungsmittel</note>
          <note>Weizen</note>
          <note>Eier</note>
          <note>Sellerie</note>
          <note>Milch und Milchprodukte (inkl. Laktose)</note>
          <note>Senf</note>
          <price role="student">5.95</price>
          <price role="employee">5.95</price>
          <price role="other">6.45</price>
        </meal>
      </category>
    </day>
    <day date="2018-08-03">
      <category name="Aktionen">
        <meal>
          <name>Rot geschmortes Huhn mit Bambussprossen und Basmatireis</name>
          <note>gelb (Ampel)</note>
          <note>Antioxidationsmittel</note>
          <note>Süßungsmittel</note>
          <note>Eier</note>
          <note>Sellerie</note>
          <note>Milch und Milchprodukte (inkl. Laktose)</note>
          <price role="student">4.95</price>
          <price role="employee">4.95</price>
          <price role="other">5.45</price>
        </meal>
      </category>
      <category name="Essen">
        <meal>
          <name>Glasnudelpfanne mit Gemüse, Austernpilzen, Zwiebeln und Sojasauce</name>
          <note>grün (Ampel)</note>
          <note>vegan</note>
          <note>konserviert</note>
          <note>Soja</note>
          <note>Schwefeldioxid und Sulfide</note>
          <price role="student">2.95</price>
          <price role="employee">2.95</price>
          <price role="other">3.45</price>
        </meal>
        <meal>
          <name>Rindergulasch nach ungarischer Art Grüne Bohnen Dampfkartoffeln</name>
          <note>grün (Ampel)</note>
          <note>Antioxidationsmittel</note>
          <price role="student">4.95</price>
          <price role="employee">4.95</price>
          <price role="other">5.45</price>
        </meal>
      </category>
    </day>
    <day date="2018-08-04">
      <closed></closed>
    </day>
    <day date="2018-08-05">
      <closed></closed>
    </day>
    <day date="2018-08-06">
      <category name="Salate">
        <meal>
          <name>Kleine Salatschale</name>
          <note>grün (Ampel)</note>
          <note>vegan</note>
          <note>Süßungsmittel</note>
          <note>Sellerie</note>
          <price role="student">1.20</price>
          <price role="employee">1.20</price>
          <price role="other">1.20</price>
        </meal>
      </category>
      <category name="Aktionen">
        <meal>
          <name>Gegrilltes Schweinerückensteak mit Röstzwiebeln, Pommes wedges und Salat</name>
          <note>rot (Ampel)</note>
          <note>Schweinefleisch bzw. mit Gelatine vom Schwein</note>
          <note>Sellerie</note>
          <note>Senf</note>
          <price role="student">4.95</price>
          <price role="employee">4.95</price>
          <price role="other">5.45</price>
        </meal>
        <meal>
          <name>Tortellini mit Käsefüllung auf Tomaten-Basilikum-Sauce</name>
          <note>gelb (Ampel)</note>
          <note>vegetarisch</note>
          <note>geschwärzt</note>
          <note>Weizen</note>
          <note>Eier</note>
          <note>Sellerie</note>
          <note>Milch und Milchprodukte (inkl. Laktose)</note>
          <price role="student">2.95</price>
          <price role="employee">2.95</price>
          <price role="other">3.45</price>
        </meal>
      </category>
      <category name="Essen">
        <meal>
          <name>Möhreneintopf mit Sonnenblumenkernen und frischem Spinat</name>
          <note>grün (Ampel)</note>
          <note>vegan</note>
          <price role="student">2.95</price>
          <price role="employee">2.95</price>
          <price role="other">3.45</price>
        </meal>
      </category>
    </day>
    <day date="2018-08-07">
      <category name="Salate">
        <meal>
          <name>Kleine Salatschale</name>
          <note>grün (Ampel)</note>
          <note>vegan</note>
          <note>Süßungsmittel</note>
          <note>Sellerie</note>
          <price role="student">1.20</price>
          <price role="employee">1.20</price>
          <price role="other">1.20</price>
        </meal>
      </category>
      <category name="Suppen">
        <meal>
          <name>Kohlrabicremesuppe</name>
          <note>gelb (Ampel)</note>
          <note>vegetarisch</note>
          <note>Milch und Milchprodukte (inkl. Laktose)</note>
          <price role="student">1.95</price>
          <price role="employee">1.95</price>
          <price role="other">2.45</price>
        </meal>
      </category>
      <category name="Aktionen">
        <meal>
          <name>Curry vom Huhn mit asiatischem Gemüse und Duftreis</name>
          <note>gelb (Ampel)</note>
          <note>Sellerie</note>
          <note>Soja</note>
          <note>Schwefeldioxid und Sulfide</note>
          <price role="student">4.95</price>
          <price role="employee">4.95</price>
          <price role="other">5.45</price>
        </meal>
      </category>
      <category name="Essen">
        <meal>
          <name>Veganes Bohnencurry mit Kokosmilch und Reis</name>
          <note>grün (Ampel)</note>
          <note>vegan</note>
          <price role="student">2.95</price>
          <price role="employee">2.95</price>
          <price role="other">3.45</price>
        </meal>
        <meal>
          <name>Makrelenfilet mit Rosmarin an Limonensauce Blattsalat mit Erdbeeren und gerösteten Mandeln</name>
          <note>gelb (Ampel)</note>
          <note>MSC</note>
          <note>Antioxidationsmittel</note>
          <note>Farbstoff</note>
          <note>Fisch</note>
          <note>Mandeln</note>
          <note>Milch und Milchprodukte (inkl. Laktose)</note>
          <note>Schwefeldioxid und Sulfide</note>
          <price role="student">5.95</price>
          <price role="employee">5.95</price>
          <price role="other">6.45</price>
        </meal>
      </category>
    </day>
    <day date="2018-08-08">
      <category name="Salate">
        <meal>
          <name>Kleine Salatschale</name>
          <note>grün (Ampel)</note>
          <note>vegan</note>
          <note>Süßungsmittel</note>
          <note>Sellerie</note>
          <price role="student">1.20</price>
          <price role="employee">1.20</price>
          <price role="other">1.20</price>
        </meal>
      </category>
      <category name="Suppen">
        <meal>
          <name>Kressecremesuppe</name>
          <note>gelb (Ampel)</note>
          <note>vegetarisch</note>
          <note>Milch und Milchprodukte (inkl. Laktose)</note>
          <price role="student">1.95</price>
          <price role="employee">1.95</price>
          <price role="other">2.45</price>
        </meal>
      </category>
      <category name="Aktionen">
        <meal>
          <name>Gegrillte Hähnchenbrust an Geflügeljus Pommes wedges Salat</name>
          <note>gelb (Ampel)</note>
          <price role="student">4.95</price>
          <price role="employee">4.95</price>
          <price role="other">5.45</price>
        </meal>
      </category>
      <category name="Essen">
        <meal>
          <name>Kartoffel-Spitzkohl-Pfanne mit Wurzelgemüse und Rinderhackfleisch</name>
          <note>grün (Ampel)</note>
          <note>mit zum Teil fein zerkleinertem Fleischanteil</note>
          <note>Sellerie</note>
          <price role="student">2.95</price>
          <price role="employee">2.95</price>
          <price role="other">3.45</price>
        </meal>
        <meal>
          <name>Kalbsgulasch nach Karlsbader Art Lauchreis und Salat</name>
          <note>grün (Ampel)</note>
          <note>Antioxidationsmittel</note>
          <note>Milch und Milchprodukte (inkl. Laktose)</note>
          <note>Sesam</note>
          <note>Senf</note>
          <price role="student">5.95</price>
          <price role="employee">5.95</price>
          <price role="other">6.45</price>
        </meal>
        <meal>
          <name>Zwei gebackene Falafelbagel an Tahin-Yofudip mit frischen Kräutern Gartengemüse würzigem Couscous</name>
          <note>grün (Ampel)</note>
          <note>vegan</note>
          <note>Antioxidationsmittel</note>
          <note>Farbstoff</note>
          <note>Weizen</note>
          <note>Soja</note>
          <note>Sesam</note>
          <note>Hefe</note>
          <price role="student">4.95</price>
          <price role="employee">4.95</price>
          <price role="other">5.45</price>
        </meal>
      </category>
    </day>
    <day date="2018-08-09">
      <category name="Salate">
        <meal>
          <name>Kleine Salatschale</name>
          <note>grün (Ampel)</note>
          <note>vegan</note>
          <note>Süßungsmittel</note>
          <note>Sellerie</note>
          <price role="student">1.20</price>
          <price role="employee">1.20</price>
          <price role="other">1.20</price>
        </meal>
      </category>
      <category name="Suppen">
        <meal>
          <name>Gemüsecremesuppe</name>
          <note>gelb (Ampel)</note>
          <note>vegetarisch</note>
          <note>Sellerie</note>
          <note>Milch und Milchprodukte (inkl. Laktose)</note>
          <price role="student">1.95</price>
          <price role="employee">1.95</price>
          <price role="other">2.45</price>
        </meal>
      </category>
      <category name="Essen">
        <meal>
          <name>Indonesisches Schweinegeschnetzeltes mit Erdnussbutter, Gemüse, Bambus Curryreis und Salat</name>
          <note>grün (Ampel)</note>
          <note>Schweinefleisch bzw. mit Gelatine vom Schwein</note>
          <note>Erdnüsse</note>
          <note>Sellerie</note>
          <note>Soja</note>
          <note>Schwefeldioxid und Sulfide</note>
          <price role="student">4.95</price>
          <price role="employee">4.95</price>
          <price role="other">5.45</price>
        </meal>
        <meal>
          <name>Ein Matjes Doppelfilet Hausfrauen Art mit Äpfeln und Zwiebeln Dillkartoffeln und Salat</name>
          <note>grün (Ampel)</note>
          <note>MSC</note>
          <note>konserviert</note>
          <note>Süßungsmittel</note>
          <note>Weizen</note>
          <note>Eier</note>
          <note>Sellerie</note>
          <note>Milch und Milchprodukte (inkl. Laktose)</note>
          <note>Senf</note>
          <price role="student">3.95</price>
          <price role="employee">3.95</price>
          <price role="other">4.45</price>
        </meal>
      </category>
    </day>
    <day date="2018-08-10">
      <category name="Salate">
        <meal>
          <name>Kleine Salatschale</name>
          <note>grün (Ampel)</note>
          <note>vegan</note>
          <note>Süßungsmittel</note>
          <note>Sellerie</note>
          <price role="student">1.20</price>
          <price role="employee">1.20</price>
          <price role="other">1.20</price>
        </meal>
      </category>
      <category name="Suppen">
        <meal>
          <name>Mangoldcremesuppe</name>
          <note>gelb (Ampel)</note>
          <note>vegetarisch</note>
          <note>Milch und Milchprodukte (inkl. Laktose)</note>
          <price role="student">1.95</price>
          <price role="employee">1.95</price>
          <price role="other">2.45</price>
        </meal>
      </category>
      <category name="Aktionen">
        <meal>
          <name>Penne rigate mit Weichkäse, Rucola und Tomaten-Basilikum-Ragout</name>
          <note>gelb (Ampel)</note>
          <note>vegetarisch</note>
          <note>Weizen</note>
          <note>Milch und Milchprodukte (inkl. Laktose)</note>
          <price role="student">2.95</price>
          <price role="employee">2.95</price>
          <price role="other">3.45</price>
        </meal>
        <meal>
          <name>Süßkartoffel-Amaranth-Burger mit Cashew-Paprika-Dip und Steakhouse Fritten</name>
          <note>gelb (Ampel)</note>
          <note>vegan</note>
          <note>Süßungsmittel</note>
          <note>Weizen</note>
          <note>Kaschunuss</note>
          <note>Sellerie</note>
          <note>Soja</note>
          <note>Sesam</note>
          <note>Hefe</note>
          <price role="student">4.95</price>
          <price role="employee">4.95</price>
          <price role="other">5.45</price>
        </meal>
        <meal>
          <name>Grünes Chili mit Rindfleisch, Paprika, frischem Koriander und Jasminreis</name>
          <note>gelb (Ampel)</note>
          <note>konserviert</note>
          <price role="student">4.95</price>
          <price role="employee">4.95</price>
          <price role="other">5.45</price>
        </meal>
      </category>
      <category name="Essen">
        <meal>
          <name>Eine gebackene Hähnchenbrust Florentiner Art an Geflügeljus Buntes Karotten-Erbsen-Gemüse Kartoffeln</name>
          <note>gelb (Ampel)</note>
          <note>Weizen</note>
          <note>Milch und Milchprodukte (inkl. Laktose)</note>
          <note>Hefe</note>
          <price role="student">4.95</price>
          <price role="employee">4.95</price>
          <price role="other">5.45</price>
        </meal>
        <meal>
          <name>Eine Scheibe Fleischkäse an Zwiebel-Kümmel-Jus mit süßem Senf Pfannengemüse</name>
          <note>gelb (Ampel)</note>
          <note>Schweinefleisch bzw. mit Gelatine vom Schwein</note>
          <note>konserviert</note>
          <note>Antioxidationsmittel</note>
          <note>Phosphat</note>
          <note>Nitritpökelsalz</note>
          <note>Senf</note>
          <price role="student">3.95</price>
          <price role="employee">3.95</price>
          <price role="other">4.45</price>
        </meal>
      </category>
    </day>
    <day date="2018-08-11">
      <closed></closed>
    </day>
    <day date="2018-08-12">
      <closed></closed>
    </day>
    <day date="2018-08-13">
      <closed></closed>
    </day>
    <day date="2018-08-14">
      <closed></closed>
    </day>
  </canteen>
</openmensa>
