<?xml version="1.0" encoding="UTF-8"?>
<openmensa version="2.1"
           xmlns="http://openmensa.org/open-mensa-v2"
           xmlns:xsi="http://www.w3.org/2001/XMLSchema-instance"
           xsi:schemaLocation="http://openmensa.org/open-mensa-v2 http://openmensa.org/open-mensa-v2.xsd">
  <canteen>
    <day date="2020-02-24">
      <category name="Salate">
        <meal>
          <name>Große Salatschale</name>
          <note>grün (Ampel)</note>
          <note>vegan</note>
          <note>Süßungsmittel</note>
          <note>Sellerie</note>
          <price role="student">1.75</price>
          <price role="employee">3.50</price>
          <price role="other">3.85</price>
        </meal>
        <meal>
          <name>Kleine Salatschale</name>
          <note>grün (Ampel)</note>
          <note>vegan</note>
          <note>Süßungsmittel</note>
          <note>Sellerie</note>
          <price role="student">0.65</price>
          <price role="employee">1.30</price>
          <price role="other">1.45</price>
        </meal>
        <meal>
          <name>Sauce Vinaigrette</name>
          <note>rot (Ampel)</note>
          <note>vegan</note>
          <note>Senf</note>
        </meal>
        <meal>
          <name>Joghurtdressing</name>
          <note>rot (Ampel)</note>
          <note>vegetarisch</note>
          <note>Antioxidationsmittel</note>
          <note>Weizen</note>
          <note>Eier</note>
          <note>Milch und Milchprodukte (inkl. Laktose)</note>
          <note>Schwefeldioxid und Sulfide</note>
          <note>Senf</note>
        </meal>
      </category>
      <category name="Essen">
        <meal>
          <name>Bulgur-Gemüse-Medaillon an Brokkolisauce</name>
          <note>gelb (Ampel)</note>
          <note>vegetarisch</note>
          <note>Antioxidationsmittel</note>
          <note>Farbstoff</note>
          <note>Weizen</note>
          <note>Eier</note>
          <note>Milch und Milchprodukte (inkl. Laktose)</note>
          <note>Hefe</note>
          <price role="student">1.75</price>
          <price role="employee">3.50</price>
          <price role="other">3.85</price>
        </meal>
        <meal>
          <name>Hühnerragout mit gerösteten Mandeln und Rosmarin</name>
          <note>gelb (Ampel)</note>
          <note>Mandeln</note>
          <price role="student">1.35</price>
          <price role="employee">2.70</price>
          <price role="other">2.95</price>
        </meal>
        <meal>
          <name>Türkische Bauernsuppe mit Paprika, Bohnen und Kartoffeln</name>
          <note>grün (Ampel)</note>
          <note>vegan</note>
          <note>Antioxidationsmittel</note>
          <price role="student">1.45</price>
          <price role="employee">2.90</price>
          <price role="other">3.20</price>
        </meal>
      </category>
      <category name="Beilagen">
        <meal>
          <name>Weiße Rübchen in Petersilienrahm</name>
          <note>grün (Ampel)</note>
          <note>vegetarisch</note>
          <note>Milch und Milchprodukte (inkl. Laktose)</note>
          <price role="student">0.60</price>
          <price role="employee">1.20</price>
          <price role="other">1.30</price>
        </meal>
        <meal>
          <name>Spiralnudeln</name>
          <note>gelb (Ampel)</note>
          <note>vegan</note>
          <note>Weizen</note>
          <price role="student">0.60</price>
          <price role="employee">1.20</price>
          <price role="other">1.30</price>
        </meal>
        <meal>
          <name>Parboiledreis mit Dinkel</name>
          <note>gelb (Ampel)</note>
          <note>vegan</note>
          <note>Dinkel</note>
          <price role="student">0.60</price>
          <price role="employee">1.20</price>
          <price role="other">1.30</price>
        </meal>
      </category>
      <category name="Desserts">
        <meal>
          <name>Cappuccinopudding</name>
          <note>gelb (Ampel)</note>
          <note>vegetarisch</note>
          <note>koffeinhaltig</note>
          <note>Milch und Milchprodukte (inkl. Laktose)</note>
          <price role="student">0.65</price>
          <price role="employee">1.30</price>
          <price role="other">1.45</price>
        </meal>
      </category>
    </day>
    <day date="2020-02-25">
      <category name="Salate">
        <meal>
          <name>Große Salatschale</name>
          <note>grün (Ampel)</note>
          <note>vegan</note>
          <note>Süßungsmittel</note>
          <note>Sellerie</note>
          <price role="student">1.75</price>
          <price role="employee">3.50</price>
          <price role="other">3.85</price>
        </meal>
        <meal>
          <name>Kleine Salatschale</name>
          <note>grün (Ampel)</note>
          <note>vegan</note>
          <note>Süßungsmittel</note>
          <note>Sellerie</note>
          <price role="student">0.65</price>
          <price role="employee">1.30</price>
          <price role="other">1.45</price>
        </meal>
        <meal>
          <name>Joghurtdressing</name>
          <note>rot (Ampel)</note>
          <note>vegetarisch</note>
          <note>Antioxidationsmittel</note>
          <note>Weizen</note>
          <note>Eier</note>
          <note>Milch und Milchprodukte (inkl. Laktose)</note>
          <note>Schwefeldioxid und Sulfide</note>
          <note>Senf</note>
        </meal>
        <meal>
          <name>Sauce Vinaigrette</name>
          <note>rot (Ampel)</note>
          <note>vegan</note>
          <note>Senf</note>
        </meal>
      </category>
      <category name="Essen">
        <meal>
          <name>Eine Hähnchenbrust mit Champignonfüllung an Tomaten-Paprika-Sauce</name>
          <note>gelb (Ampel)</note>
          <note>Antioxidationsmittel</note>
          <note>Farbstoff</note>
          <note>Milch und Milchprodukte (inkl. Laktose)</note>
          <note>Schwefeldioxid und Sulfide</note>
          <price role="student">2.15</price>
          <price role="employee">4.30</price>
          <price role="other">4.75</price>
        </meal>
        <meal>
          <name>Eine Brokkoli-Nuss-Ecke mit Joghurt-Apfeldip</name>
          <note>gelb (Ampel)</note>
          <note>vegetarisch</note>
          <note>Antioxidationsmittel</note>
          <note>Farbstoff</note>
          <note>Weizen</note>
          <note>Mandeln</note>
          <note>Haselnuss</note>
          <note>Sellerie</note>
          <note>Milch und Milchprodukte (inkl. Laktose)</note>
          <note>Hefe</note>
          <price role="student">1.55</price>
          <price role="employee">3.10</price>
          <price role="other">3.40</price>
        </meal>
        <meal>
          <name>Ungarisches Kartoffelgulasch mit Ajvar, Paprika und Majoran</name>
          <note>grün (Ampel)</note>
          <note>vegan</note>
          <note>Schwefeldioxid und Sulfide</note>
          <price role="student">1.45</price>
          <price role="employee">2.90</price>
          <price role="other">3.20</price>
        </meal>
      </category>
      <category name="Beilagen">
        <meal>
          <name>Rosenkohl</name>
          <note>grün (Ampel)</note>
          <note>vegan</note>
          <price role="student">0.60</price>
          <price role="employee">1.20</price>
          <price role="other">1.30</price>
        </meal>
        <meal>
          <name>Kartoffelbällchen</name>
          <note>gelb (Ampel)</note>
          <note>vegetarisch</note>
          <price role="student">0.75</price>
          <price role="employee">1.50</price>
          <price role="other">1.65</price>
        </meal>
        <meal>
          <name>Vollkorn Penne rigate</name>
          <note>grün (Ampel)</note>
          <note>vegan</note>
          <note>Weizen</note>
          <price role="student">0.60</price>
          <price role="employee">1.20</price>
          <price role="other">1.30</price>
        </meal>
      </category>
      <category name="Desserts">
        <meal>
          <name>Mango-Maracuja-Pudding</name>
          <note>gelb (Ampel)</note>
          <note>vegetarisch</note>
          <note>Milch und Milchprodukte (inkl. Laktose)</note>
          <price role="student">0.65</price>
          <price role="employee">1.30</price>
          <price role="other">1.45</price>
        </meal>
      </category>
    </day>
    <day date="2020-02-26">
      <category name="Salate">
        <meal>
          <name>Große Salatschale</name>
          <note>grün (Ampel)</note>
          <note>vegan</note>
          <note>Süßungsmittel</note>
          <note>Sellerie</note>
          <price role="student">1.75</price>
          <price role="employee">3.50</price>
          <price role="other">3.85</price>
        </meal>
        <meal>
          <name>Kleine Salatschale</name>
          <note>grün (Ampel)</note>
          <note>vegan</note>
          <note>Süßungsmittel</note>
          <note>Sellerie</note>
          <price role="student">0.65</price>
          <price role="employee">1.30</price>
          <price role="other">1.45</price>
        </meal>
        <meal>
          <name>Joghurtdressing</name>
          <note>rot (Ampel)</note>
          <note>vegetarisch</note>
          <note>Antioxidationsmittel</note>
          <note>Weizen</note>
          <note>Eier</note>
          <note>Milch und Milchprodukte (inkl. Laktose)</note>
          <note>Schwefeldioxid und Sulfide</note>
          <note>Senf</note>
        </meal>
        <meal>
          <name>Sauce Vinaigrette</name>
          <note>rot (Ampel)</note>
          <note>vegan</note>
          <note>Senf</note>
        </meal>
      </category>
      <category name="Essen">
        <meal>
          <name>Schweinegulasch mit Bohnen und saurer Sahne</name>
          <note>gelb (Ampel)</note>
          <note>Schweinefleisch bzw. mit Gelatine vom Schwein</note>
          <note>Antioxidationsmittel</note>
          <note>Milch und Milchprodukte (inkl. Laktose)</note>
          <price role="student">1.55</price>
          <price role="employee">3.10</price>
          <price role="other">3.40</price>
        </meal>
        <meal>
          <name>Zwei gebackene Kohlrabimedaillons an Dill-Senfrahm</name>
          <note>gelb (Ampel)</note>
          <note>vegetarisch</note>
          <note>Weizen</note>
          <note>Eier</note>
          <note>Milch und Milchprodukte (inkl. Laktose)</note>
          <note>Senf</note>
          <price role="student">1.35</price>
          <price role="employee">2.70</price>
          <price role="other">2.95</price>
        </meal>
        <meal>
          <name>Hirsepüree an Champignonrahmsauce</name>
          <note>gelb (Ampel)</note>
          <note>vegetarisch</note>
          <note>Antioxidationsmittel</note>
          <note>Milch und Milchprodukte (inkl. Laktose)</note>
          <price role="student">1.45</price>
          <price role="employee">2.90</price>
          <price role="other">3.20</price>
        </meal>
      </category>
      <category name="Beilagen">
        <meal>
          <name>Romanesco</name>
          <note>grün (Ampel)</note>
          <note>vegan</note>
          <price role="student">0.60</price>
          <price role="employee">1.20</price>
          <price role="other">1.30</price>
        </meal>
        <meal>
          <name>Kartoffel-Kräuter-Püree</name>
          <note>gelb (Ampel)</note>
          <note>vegetarisch</note>
          <note>Antioxidationsmittel</note>
          <note>Phosphat</note>
          <note>Milch und Milchprodukte (inkl. Laktose)</note>
          <note>Schwefeldioxid und Sulfide</note>
          <price role="student">0.75</price>
          <price role="employee">1.50</price>
          <price role="other">1.65</price>
        </meal>
        <meal>
          <name>Dreikornrisotto</name>
          <note>gelb (Ampel)</note>
          <note>vegan</note>
          <note>Roggen</note>
          <note>Dinkel</note>
          <price role="student">0.60</price>
          <price role="employee">1.20</price>
          <price role="other">1.30</price>
        </meal>
      </category>
      <category name="Desserts">
        <meal>
          <name>Schokoladenpudding</name>
          <note>gelb (Ampel)</note>
          <note>vegetarisch</note>
          <note>Soja</note>
          <note>Milch und Milchprodukte (inkl. Laktose)</note>
          <price role="student">0.65</price>
          <price role="employee">1.30</price>
          <price role="other">1.45</price>
        </meal>
      </category>
    </day>
    <day date="2020-02-27">
      <category name="Salate">
        <meal>
          <name>Große Salatschale</name>
          <note>grün (Ampel)</note>
          <note>vegan</note>
          <note>Süßungsmittel</note>
          <note>Sellerie</note>
          <price role="student">1.75</price>
          <price role="employee">3.50</price>
          <price role="other">3.85</price>
        </meal>
        <meal>
          <name>Kleine Salatschale</name>
          <note>grün (Ampel)</note>
          <note>vegan</note>
          <note>Süßungsmittel</note>
          <note>Sellerie</note>
          <price role="student">0.65</price>
          <price role="employee">1.30</price>
          <price role="other">1.45</price>
        </meal>
        <meal>
          <name>Joghurtdressing</name>
          <note>rot (Ampel)</note>
          <note>vegetarisch</note>
          <note>Antioxidationsmittel</note>
          <note>Weizen</note>
          <note>Eier</note>
          <note>Milch und Milchprodukte (inkl. Laktose)</note>
          <note>Schwefeldioxid und Sulfide</note>
          <note>Senf</note>
        </meal>
        <meal>
          <name>Sauce Vinaigrette</name>
          <note>rot (Ampel)</note>
          <note>vegan</note>
          <note>Senf</note>
        </meal>
      </category>
      <category name="Essen">
        <meal>
          <name>Eine Brokkoli-Nuss-Ecke an scharfer Erdnuss-Kokos-Sauce</name>
          <note>rot (Ampel)</note>
          <note>vegan</note>
          <note>konserviert</note>
          <note>Antioxidationsmittel</note>
          <note>Farbstoff</note>
          <note>Weizen</note>
          <note>Erdnüsse</note>
          <note>Mandeln</note>
          <note>Haselnuss</note>
          <note>Sellerie</note>
          <note>Soja</note>
          <note>Hefe</note>
          <price role="student">1.55</price>
          <price role="employee">3.10</price>
          <price role="other">3.40</price>
        </meal>
        <meal>
          <name>Schwarzwurzel-Kartoffel-Auflauf mit Karotten an Kräutersauce</name>
          <note>grün (Ampel)</note>
          <note>vegetarisch</note>
          <note>Antioxidationsmittel</note>
          <note>Weizen</note>
          <note>Soja</note>
          <note>Milch und Milchprodukte (inkl. Laktose)</note>
          <note>Hefe</note>
          <price role="student">1.45</price>
          <price role="employee">2.90</price>
          <price role="other">3.20</price>
        </meal>
      </category>
      <category name="Beilagen">
        <meal>
          <name>Balkangemüse</name>
          <note>grün (Ampel)</note>
          <note>vegan</note>
          <note>Sellerie</note>
          <price role="student">0.60</price>
          <price role="employee">1.20</price>
          <price role="other">1.30</price>
        </meal>
        <meal>
          <name>Backkartoffeln</name>
          <note>grün (Ampel)</note>
          <note>vegan</note>
          <price role="student">0.75</price>
          <price role="employee">1.50</price>
          <price role="other">1.65</price>
        </meal>
        <meal>
          <name>Farfalle</name>
          <note>gelb (Ampel)</note>
          <note>vegan</note>
          <note>Weizen</note>
          <price role="student">0.60</price>
          <price role="employee">1.20</price>
          <price role="other">1.30</price>
        </meal>
      </category>
    </day>
    <day date="2020-02-28">
      <category name="Salate">
        <meal>
          <name>Große Salatschale</name>
          <note>grün (Ampel)</note>
          <note>vegan</note>
          <note>Süßungsmittel</note>
          <note>Sellerie</note>
          <price role="student">1.75</price>
          <price role="employee">3.50</price>
          <price role="other">3.85</price>
        </meal>
        <meal>
          <name>Kleine Salatschale</name>
          <note>grün (Ampel)</note>
          <note>vegan</note>
          <note>Süßungsmittel</note>
          <note>Sellerie</note>
          <price role="student">0.65</price>
          <price role="employee">1.30</price>
          <price role="other">1.45</price>
        </meal>
        <meal>
          <name>Joghurtdressing</name>
          <note>rot (Ampel)</note>
          <note>vegetarisch</note>
          <note>Antioxidationsmittel</note>
          <note>Weizen</note>
          <note>Eier</note>
          <note>Milch und Milchprodukte (inkl. Laktose)</note>
          <note>Schwefeldioxid und Sulfide</note>
          <note>Senf</note>
        </meal>
        <meal>
          <name>Sauce Vinaigrette</name>
          <note>rot (Ampel)</note>
          <note>vegan</note>
          <note>Senf</note>
        </meal>
      </category>
      <category name="Essen">
        <meal>
          <name>Eine gebackene Seelachsroulade mit Gemüsefüllung an Senf-Honig-Sauce</name>
          <note>gelb (Ampel)</note>
          <note>MSC</note>
          <note>Antioxidationsmittel</note>
          <note>Phosphat</note>
          <note>Weizen</note>
          <note>Gerste</note>
          <note>Fisch</note>
          <note>Sellerie</note>
          <note>Milch und Milchprodukte (inkl. Laktose)</note>
          <note>Hefe</note>
          <note>Senf</note>
          <price role="student">2.15</price>
          <price role="employee">4.30</price>
          <price role="other">4.75</price>
        </meal>
        <meal>
          <name>Chilenische Bohnen mit Kürbis, Birnen und Mais</name>
          <note>grün (Ampel)</note>
          <note>vegan</note>
          <note>konserviert</note>
          <note>Antioxidationsmittel</note>
          <note>Senf</note>
          <price role="student">1.45</price>
          <price role="employee">2.90</price>
          <price role="other">3.20</price>
        </meal>
      </category>
      <category name="Beilagen">
        <meal>
          <name>Geschmorter Fenchel mit Paprika</name>
          <note>grün (Ampel)</note>
          <note>vegan</note>
          <price role="student">0.60</price>
          <price role="employee">1.20</price>
          <price role="other">1.30</price>
        </meal>
        <meal>
          <name>Kartoffelsalat mit Joghurt</name>
          <note>grün (Ampel)</note>
          <note>vegetarisch</note>
          <note>Süßungsmittel</note>
          <note>Weizen</note>
          <note>Eier</note>
          <note>Milch und Milchprodukte (inkl. Laktose)</note>
          <note>Hefe</note>
          <note>Senf</note>
          <price role="student">0.75</price>
          <price role="employee">1.50</price>
          <price role="other">1.65</price>
        </meal>
        <meal>
          <name>Salzkartoffeln</name>
          <note>grün (Ampel)</note>
          <note>vegan</note>
          <price role="student">0.60</price>
          <price role="employee">1.20</price>
          <price role="other">1.30</price>
        </meal>
      </category>
    </day>
    <day date="2020-02-29">
      <closed></closed>
    </day>
    <day date="2020-03-01">
      <closed></closed>
    </day>
    <day date="2020-03-02">
      <category name="Vorspeisen">
        <meal>
          <name>Bulgursalat mit frischer Minze</name>
          <note>gelb (Ampel)</note>
          <note>vegan</note>
          <note>Antioxidationsmittel</note>
          <note>Weizen</note>
          <price role="student">1.45</price>
          <price role="employee">1.60</price>
          <price role="other">1.75</price>
        </meal>
      </category>
      <category name="Salate">
        <meal>
          <name>Große Salatschale</name>
          <note>grün (Ampel)</note>
          <note>vegan</note>
          <note>Süßungsmittel</note>
          <note>Sellerie</note>
          <price role="student">1.75</price>
          <price role="employee">3.50</price>
          <price role="other">3.85</price>
        </meal>
        <meal>
          <name>Kleine Salatschale</name>
          <note>grün (Ampel)</note>
          <note>vegan</note>
          <note>Süßungsmittel</note>
          <note>Sellerie</note>
          <price role="student">0.65</price>
          <price role="employee">1.30</price>
          <price role="other">1.45</price>
        </meal>
        <meal>
          <name>Joghurtdressing</name>
          <note>rot (Ampel)</note>
          <note>vegetarisch</note>
          <note>Antioxidationsmittel</note>
          <note>Weizen</note>
          <note>Eier</note>
          <note>Milch und Milchprodukte (inkl. Laktose)</note>
          <note>Schwefeldioxid und Sulfide</note>
          <note>Senf</note>
        </meal>
        <meal>
          <name>Sauce Vinaigrette</name>
          <note>rot (Ampel)</note>
          <note>vegan</note>
          <note>Senf</note>
        </meal>
      </category>
      <category name="Essen">
        <meal>
          <name>Eine Wirsingkohlroulade mit Hackfleischfüllung an Bratensauce</name>
          <note>gelb (Ampel)</note>
          <note>Schweinefleisch bzw. mit Gelatine vom Schwein</note>
          <note>Antioxidationsmittel</note>
          <note>mit zum Teil fein zerkleinertem Fleischanteil</note>
          <note>Weizen</note>
          <note>Hefe</note>
          <note>Senf</note>
          <price role="student">1.35</price>
          <price role="employee">2.70</price>
          <price role="other">2.95</price>
        </meal>
        <meal>
          <name>Berliner Erbseneintopf mit Wurzelgemüse und frischer Blattpetersilie</name>
          <note>grün (Ampel)</note>
          <note>vegan</note>
          <note>Sellerie</note>
          <price role="student">1.45</price>
          <price role="employee">2.90</price>
          <price role="other">3.20</price>
        </meal>
      </category>
      <category name="Beilagen">
        <meal>
          <name>Glacierte Fingermöhrchen</name>
          <note>grün (Ampel)</note>
          <note>vegan</note>
          <price role="student">0.60</price>
          <price role="employee">1.20</price>
          <price role="other">1.30</price>
        </meal>
        <meal>
          <name>Petersilienkartoffeln</name>
          <note>grün (Ampel)</note>
          <note>vegan</note>
          <price role="student">0.60</price>
          <price role="employee">1.20</price>
          <price role="other">1.30</price>
        </meal>
      </category>
      <category name="Desserts">
        <meal>
          <name>Rote Grütze mit Beeren Vanillesauce</name>
          <note>grün (Ampel)</note>
          <note>vegan</note>
          <note>Farbstoff</note>
          <note>Soja</note>
          <price role="student">0.70</price>
          <price role="employee">1.40</price>
          <price role="other">1.55</price>
        </meal>
      </category>
    </day>
    <day date="2020-03-03">
      <category name="Salate">
        <meal>
          <name>Große Salatschale</name>
          <note>grün (Ampel)</note>
          <note>vegan</note>
          <note>Süßungsmittel</note>
          <note>Sellerie</note>
          <price role="student">1.75</price>
          <price role="employee">3.50</price>
          <price role="other">3.85</price>
        </meal>
        <meal>
          <name>Kleine Salatschale</name>
          <note>grün (Ampel)</note>
          <note>vegan</note>
          <note>Süßungsmittel</note>
          <note>Sellerie</note>
          <price role="student">0.65</price>
          <price role="employee">1.30</price>
          <price role="other">1.45</price>
        </meal>
        <meal>
          <name>Joghurtdressing</name>
          <note>rot (Ampel)</note>
          <note>vegetarisch</note>
          <note>Antioxidationsmittel</note>
          <note>Weizen</note>
          <note>Eier</note>
          <note>Milch und Milchprodukte (inkl. Laktose)</note>
          <note>Schwefeldioxid und Sulfide</note>
          <note>Senf</note>
        </meal>
        <meal>
          <name>Sauce Vinaigrette</name>
          <note>rot (Ampel)</note>
          <note>vegan</note>
          <note>Senf</note>
        </meal>
      </category>
      <category name="Essen">
        <meal>
          <name>Eine Rinderroulade mit Speck in Schmorsauce</name>
          <note>gelb (Ampel)</note>
          <note>Schweinefleisch bzw. mit Gelatine vom Schwein</note>
          <note>Antioxidationsmittel</note>
          <note>Süßungsmittel</note>
          <note>Sellerie</note>
          <note>Senf</note>
          <price role="student">2.45</price>
          <price role="employee">4.90</price>
          <price role="other">5.40</price>
        </meal>
        <meal>
          <name>Italienische Nudeln mit Tomatensugo und frischem Basilikum</name>
          <note>gelb (Ampel)</note>
          <note>vegan</note>
          <note>Antioxidationsmittel</note>
          <note>Weizen</note>
          <price role="student">1.45</price>
          <price role="employee">2.90</price>
          <price role="other">3.20</price>
        </meal>
      </category>
      <category name="Beilagen">
        <meal>
          <name>Apfelrotkohl</name>
          <note>grün (Ampel)</note>
          <note>vegan</note>
          <note>Antioxidationsmittel</note>
          <price role="student">0.60</price>
          <price role="employee">1.20</price>
          <price role="other">1.30</price>
        </meal>
        <meal>
          <name>Zwei Kartoffelklöße</name>
          <note>grün (Ampel)</note>
          <note>vegan</note>
          <price role="student">0.75</price>
          <price role="employee">1.50</price>
          <price role="other">1.65</price>
        </meal>
      </category>
    </day>
    <day date="2020-03-04">
      <category name="Salate">
        <meal>
          <name>Große Salatschale</name>
          <note>grün (Ampel)</note>
          <note>vegan</note>
          <note>Süßungsmittel</note>
          <note>Sellerie</note>
          <price role="student">1.75</price>
          <price role="employee">3.50</price>
          <price role="other">3.85</price>
        </meal>
        <meal>
          <name>Kleine Salatschale</name>
          <note>grün (Ampel)</note>
          <note>vegan</note>
          <note>Süßungsmittel</note>
          <note>Sellerie</note>
          <price role="student">0.65</price>
          <price role="employee">1.30</price>
          <price role="other">1.45</price>
        </meal>
        <meal>
          <name>Joghurtdressing</name>
          <note>rot (Ampel)</note>
          <note>vegetarisch</note>
          <note>Antioxidationsmittel</note>
          <note>Weizen</note>
          <note>Eier</note>
          <note>Milch und Milchprodukte (inkl. Laktose)</note>
          <note>Schwefeldioxid und Sulfide</note>
          <note>Senf</note>
        </meal>
        <meal>
          <name>Sauce Vinaigrette</name>
          <note>rot (Ampel)</note>
          <note>vegan</note>
          <note>Senf</note>
        </meal>
      </category>
      <category name="Essen">
        <meal>
          <name>Thüringer Rostbrätl an Majoransauce</name>
          <note>gelb (Ampel)</note>
          <note>Schweinefleisch bzw. mit Gelatine vom Schwein</note>
          <note>Antioxidationsmittel</note>
          <note>Gerste</note>
          <note>Senf</note>
          <price role="student">1.75</price>
          <price role="employee">3.50</price>
          <price role="other">3.85</price>
        </meal>
        <meal>
          <name>Vegane Reispfanne Paella</name>
          <note>grün (Ampel)</note>
          <note>vegan</note>
          <price role="student">1.45</price>
          <price role="employee">2.90</price>
          <price role="other">3.20</price>
        </meal>
      </category>
      <category name="Beilagen">
        <meal>
          <name>Brokkoli</name>
          <note>grün (Ampel)</note>
          <note>vegan</note>
          <price role="student">0.60</price>
          <price role="employee">1.20</price>
          <price role="other">1.30</price>
        </meal>
        <meal>
          <name>Bratkartoffeln</name>
          <note>grün (Ampel)</note>
          <note>vegan</note>
          <price role="student">0.75</price>
          <price role="employee">1.50</price>
          <price role="other">1.65</price>
        </meal>
      </category>
      <category name="Desserts">
        <meal>
          <name>Schokoladenpudding</name>
          <note>gelb (Ampel)</note>
          <note>vegetarisch</note>
          <note>Soja</note>
          <note>Milch und Milchprodukte (inkl. Laktose)</note>
          <price role="student">0.65</price>
          <price role="employee">1.30</price>
          <price role="other">1.45</price>
        </meal>
      </category>
    </day>
    <day date="2020-03-05">
      <category name="Salate">
        <meal>
          <name>Große Salatschale</name>
          <note>grün (Ampel)</note>
          <note>vegan</note>
          <note>Süßungsmittel</note>
          <note>Sellerie</note>
          <price role="student">1.75</price>
          <price role="employee">3.50</price>
          <price role="other">3.85</price>
        </meal>
        <meal>
          <name>Kleine Salatschale</name>
          <note>grün (Ampel)</note>
          <note>vegan</note>
          <note>Süßungsmittel</note>
          <note>Sellerie</note>
          <price role="student">0.65</price>
          <price role="employee">1.30</price>
          <price role="other">1.45</price>
        </meal>
        <meal>
          <name>Joghurtdressing</name>
          <note>rot (Ampel)</note>
          <note>vegetarisch</note>
          <note>Antioxidationsmittel</note>
          <note>Weizen</note>
          <note>Eier</note>
          <note>Milch und Milchprodukte (inkl. Laktose)</note>
          <note>Schwefeldioxid und Sulfide</note>
          <note>Senf</note>
        </meal>
        <meal>
          <name>Sauce Vinaigrette</name>
          <note>rot (Ampel)</note>
          <note>vegan</note>
          <note>Senf</note>
        </meal>
      </category>
      <category name="Essen">
        <meal>
          <name>Zwei Sesam-Karotten-Sticks an Curry-Mango-Sauce</name>
          <note>gelb (Ampel)</note>
          <note>vegan</note>
          <note>Antioxidationsmittel</note>
          <note>Weizen</note>
          <note>Sellerie</note>
          <note>Soja</note>
          <note>Sesam</note>
          <price role="student">1.95</price>
          <price role="employee">3.90</price>
          <price role="other">4.30</price>
        </meal>
        <meal>
          <name>Kartoffel-Gemüse-Auflauf an Paprikasauce</name>
          <note>grün (Ampel)</note>
          <note>vegetarisch</note>
          <note>Eier</note>
          <note>Sellerie</note>
          <note>Milch und Milchprodukte (inkl. Laktose)</note>
          <price role="student">1.45</price>
          <price role="employee">2.90</price>
          <price role="other">3.20</price>
        </meal>
      </category>
      <category name="Beilagen">
        <meal>
          <name>Kräutermais</name>
          <note>grün (Ampel)</note>
          <note>vegan</note>
          <price role="student">0.60</price>
          <price role="employee">1.20</price>
          <price role="other">1.30</price>
        </meal>
        <meal>
          <name>Langkornreis mit Röstzwiebeln</name>
          <note>gelb (Ampel)</note>
          <note>vegan</note>
          <note>Weizen</note>
          <price role="student">0.60</price>
          <price role="employee">1.20</price>
          <price role="other">1.30</price>
        </meal>
      </category>
    </day>
    <day date="2020-03-06">
      <category name="Salate">
        <meal>
          <name>Große Salatschale</name>
          <note>grün (Ampel)</note>
          <note>vegan</note>
          <note>Süßungsmittel</note>
          <note>Sellerie</note>
          <price role="student">1.75</price>
          <price role="employee">3.50</price>
          <price role="other">3.85</price>
        </meal>
        <meal>
          <name>Kleine Salatschale</name>
          <note>grün (Ampel)</note>
          <note>vegan</note>
          <note>Süßungsmittel</note>
          <note>Sellerie</note>
          <price role="student">0.65</price>
          <price role="employee">1.30</price>
          <price role="other">1.45</price>
        </meal>
        <meal>
          <name>Joghurtdressing</name>
          <note>rot (Ampel)</note>
          <note>vegetarisch</note>
          <note>Antioxidationsmittel</note>
          <note>Weizen</note>
          <note>Eier</note>
          <note>Milch und Milchprodukte (inkl. Laktose)</note>
          <note>Schwefeldioxid und Sulfide</note>
          <note>Senf</note>
        </meal>
        <meal>
          <name>Sauce Vinaigrette</name>
          <note>rot (Ampel)</note>
          <note>vegan</note>
          <note>Senf</note>
        </meal>
      </category>
      <category name="Essen">
        <meal>
          <name>Ein gebackenes Seelachsfilet an Kräuterremoulade</name>
          <note>rot (Ampel)</note>
          <note>MSC</note>
          <note>Antioxidationsmittel</note>
          <note>Süßungsmittel</note>
          <note>Weizen</note>
          <note>Eier</note>
          <note>Milch und Milchprodukte (inkl. Laktose)</note>
          <note>Hefe</note>
          <note>Senf</note>
          <price role="student">1.35</price>
          <price role="employee">2.70</price>
          <price role="other">2.95</price>
        </meal>
        <meal>
          <name>Blumenkohl in Kräuter-Senf-Sauce und Dampfkartoffeln</name>
          <note>gelb (Ampel)</note>
          <note>vegan</note>
          <note>Antioxidationsmittel</note>
          <note>Soja</note>
          <note>Senf</note>
          <price role="student">1.45</price>
          <price role="employee">2.90</price>
          <price role="other">3.20</price>
        </meal>
      </category>
      <category name="Beilagen">
        <meal>
          <name>Balkangemüse</name>
          <note>grün (Ampel)</note>
          <note>vegan</note>
          <note>Sellerie</note>
          <price role="student">0.60</price>
          <price role="employee">1.20</price>
          <price role="other">1.30</price>
        </meal>
        <meal>
          <name>Bunter Kartoffelsalat Süddeutsche Art</name>
          <note>grün (Ampel)</note>
          <note>vegan</note>
          <note>Senf</note>
          <price role="student">0.75</price>
          <price role="employee">1.50</price>
          <price role="other">1.65</price>
        </meal>
        <meal>
          <name>Rosmarinkartoffeln</name>
          <note>grün (Ampel)</note>
          <note>vegan</note>
          <price role="student">0.75</price>
          <price role="employee">1.50</price>
          <price role="other">1.65</price>
        </meal>
        <meal>
          <name>Schnittlauchkartoffeln</name>
          <note>grün (Ampel)</note>
          <note>vegan</note>
          <price role="student">0.60</price>
          <price role="employee">1.20</price>
          <price role="other">1.30</price>
        </meal>
      </category>
    </day>
    <day date="2020-03-07">
      <closed></closed>
    </day>
    <day date="2020-03-08">
      <closed></closed>
    </day>
    <day date="2020-03-09">
      <category name="Salate">
        <meal>
          <name>Große Salatschale</name>
          <note>grün (Ampel)</note>
          <note>vegan</note>
          <note>Süßungsmittel</note>
          <note>Sellerie</note>
          <price role="student">1.75</price>
          <price role="employee">3.50</price>
          <price role="other">3.85</price>
        </meal>
        <meal>
          <name>Kleine Salatschale</name>
          <note>grün (Ampel)</note>
          <note>vegan</note>
          <note>Süßungsmittel</note>
          <note>Sellerie</note>
          <price role="student">0.65</price>
          <price role="employee">1.30</price>
          <price role="other">1.45</price>
        </meal>
        <meal>
          <name>Sauce Vinaigrette</name>
          <note>rot (Ampel)</note>
          <note>vegan</note>
          <note>Senf</note>
        </meal>
        <meal>
          <name>Joghurtdressing</name>
          <note>rot (Ampel)</note>
          <note>vegetarisch</note>
          <note>Antioxidationsmittel</note>
          <note>Weizen</note>
          <note>Eier</note>
          <note>Milch und Milchprodukte (inkl. Laktose)</note>
          <note>Schwefeldioxid und Sulfide</note>
          <note>Senf</note>
        </meal>
      </category>
      <category name="Essen">
        <meal>
          <name>Ein Quinoa-Chili-Medaillon an Tomaten-Ingwer-Sauce</name>
          <note>rot (Ampel)</note>
          <note>vegetarisch</note>
          <note>Antioxidationsmittel</note>
          <note>Farbstoff</note>
          <note>Weizen</note>
          <note>Eier</note>
          <note>Milch und Milchprodukte (inkl. Laktose)</note>
          <note>Hefe</note>
          <price role="student">1.75</price>
          <price role="employee">3.50</price>
          <price role="other">3.85</price>
        </meal>
        <meal>
          <name>Eine gebackene Hähnchenbrust im Knuspermantel an Geflügeljus</name>
          <note>gelb (Ampel)</note>
          <note>Weizen</note>
          <note>Hefe</note>
          <price role="student">1.55</price>
          <price role="employee">3.10</price>
          <price role="other">3.40</price>
        </meal>
        <meal>
          <name>Berliner Erbseneintopf mit Wurzelgemüse und frischer Blattpetersilie</name>
          <note>grün (Ampel)</note>
          <note>vegan</note>
          <note>Sellerie</note>
          <price role="student">1.45</price>
          <price role="employee">2.90</price>
          <price role="other">3.20</price>
        </meal>
      </category>
      <category name="Beilagen">
        <meal>
          <name>Zucchini-Tomaten-Gemüse</name>
          <note>grün (Ampel)</note>
          <note>vegan</note>
          <price role="student">0.60</price>
          <price role="employee">1.20</price>
          <price role="other">1.30</price>
        </meal>
        <meal>
          <name>Backkartoffeln</name>
          <note>grün (Ampel)</note>
          <note>vegan</note>
          <price role="student">0.75</price>
          <price role="employee">1.50</price>
          <price role="other">1.65</price>
        </meal>
        <meal>
          <name>Rigatoni</name>
          <note>gelb (Ampel)</note>
          <note>vegan</note>
          <note>Weizen</note>
          <price role="student">0.60</price>
          <price role="employee">1.20</price>
          <price role="other">1.30</price>
        </meal>
      </category>
    </day>
    <day date="2020-03-10">
      <category name="Salate">
        <meal>
          <name>Große Salatschale</name>
          <note>grün (Ampel)</note>
          <note>vegan</note>
          <note>Süßungsmittel</note>
          <note>Sellerie</note>
          <price role="student">1.75</price>
          <price role="employee">3.50</price>
          <price role="other">3.85</price>
        </meal>
        <meal>
          <name>Kleine Salatschale</name>
          <note>grün (Ampel)</note>
          <note>vegan</note>
          <note>Süßungsmittel</note>
          <note>Sellerie</note>
          <price role="student">0.65</price>
          <price role="employee">1.30</price>
          <price role="other">1.45</price>
        </meal>
        <meal>
          <name>Joghurtdressing</name>
          <note>rot (Ampel)</note>
          <note>vegetarisch</note>
          <note>Antioxidationsmittel</note>
          <note>Weizen</note>
          <note>Eier</note>
          <note>Milch und Milchprodukte (inkl. Laktose)</note>
          <note>Schwefeldioxid und Sulfide</note>
          <note>Senf</note>
        </meal>
        <meal>
          <name>Sauce Vinaigrette</name>
          <note>rot (Ampel)</note>
          <note>vegan</note>
          <note>Senf</note>
        </meal>
      </category>
      <category name="Aktionen">
        <meal>
          <name>Penne rigate mit Bärlauchpesto</name>
          <note>gelb (Ampel)</note>
          <note>vegan</note>
          <note>Antioxidationsmittel</note>
          <note>Weizen</note>
          <note>Mandeln</note>
          <price role="student">3.95</price>
          <price role="employee">4.35</price>
          <price role="other">4.75</price>
        </meal>
      </category>
      <category name="Essen">
        <meal>
          <name>Eine Bratwurst Thüringer Art an Majoransauce</name>
          <note>rot (Ampel)</note>
          <note>Schweinefleisch bzw. mit Gelatine vom Schwein</note>
          <note>Antioxidationsmittel</note>
          <note>Senf</note>
          <price role="student">1.55</price>
          <price role="employee">3.10</price>
          <price role="other">3.40</price>
        </meal>
        <meal>
          <name>Zwei Schwarzwurzelmedaillons in Kräuter-Senf-Sauce</name>
          <note>gelb (Ampel)</note>
          <note>vegetarisch</note>
          <note>Antioxidationsmittel</note>
          <note>Weizen</note>
          <note>Sellerie</note>
          <note>Soja</note>
          <note>Milch und Milchprodukte (inkl. Laktose)</note>
          <note>Sesam</note>
          <note>Hefe</note>
          <note>Senf</note>
          <price role="student">1.35</price>
          <price role="employee">2.70</price>
          <price role="other">2.95</price>
        </meal>
        <meal>
          <name>Spinat-Kartoffel-Eintopf mit Weichkäse</name>
          <note>grün (Ampel)</note>
          <note>vegetarisch</note>
          <note>Sellerie</note>
          <note>Milch und Milchprodukte (inkl. Laktose)</note>
          <price role="student">1.45</price>
          <price role="employee">2.90</price>
          <price role="other">3.20</price>
        </meal>
      </category>
      <category name="Beilagen">
        <meal>
          <name>Karottengemüse</name>
          <note>grün (Ampel)</note>
          <note>vegan</note>
          <price role="student">0.60</price>
          <price role="employee">1.20</price>
          <price role="other">1.30</price>
        </meal>
        <meal>
          <name>Pommes frites</name>
          <note>gelb (Ampel)</note>
          <note>vegan</note>
          <price role="student">0.75</price>
          <price role="employee">1.50</price>
          <price role="other">1.65</price>
        </meal>
        <meal>
          <name>Petersilienkartoffeln</name>
          <note>grün (Ampel)</note>
          <note>vegan</note>
          <price role="student">0.60</price>
          <price role="employee">1.20</price>
          <price role="other">1.30</price>
        </meal>
      </category>
    </day>
    <day date="2020-03-11">
      <category name="Essen">
        <meal>
          <name>Ein Seelachsfilet nach Spreewälder Art an Dillrahmsauce</name>
          <note>grün (Ampel)</note>
          <note>MSC</note>
          <note>Antioxidationsmittel</note>
          <note>Weizen</note>
          <note>Gerste</note>
          <note>Fisch</note>
          <note>Sellerie</note>
          <note>Milch und Milchprodukte (inkl. Laktose)</note>
          <note>Schwefeldioxid und Sulfide</note>
          <price role="student">2.15</price>
          <price role="employee">4.30</price>
          <price role="other">4.75</price>
        </meal>
        <meal>
          <name>Vegetarische Paprikaschote Orientalische Art mit Datteln und Feigen an Kurkumasauce</name>
          <note>gelb (Ampel)</note>
          <note>vegetarisch</note>
          <note>Weizen</note>
          <note>Eier</note>
          <note>Sellerie</note>
          <note>Soja</note>
          <note>Milch und Milchprodukte (inkl. Laktose)</note>
          <price role="student">1.55</price>
          <price role="employee">3.10</price>
          <price role="other">3.40</price>
        </meal>
        <meal>
          <name>Tessiner Pilzrisotto mit Petersilie</name>
          <note>gelb (Ampel)</note>
          <note>konserviert</note>
          <note>Antioxidationsmittel</note>
          <note>Eier</note>
          <note>Sellerie</note>
          <note>Milch und Milchprodukte (inkl. Laktose)</note>
          <price role="student">1.45</price>
          <price role="employee">2.90</price>
          <price role="other">3.20</price>
        </meal>
        <meal>
          <name>Tiroler Kaiserschmarrn mit warmer Zwetschgensauce</name>
          <note>rot (Ampel)</note>
          <note>vegetarisch</note>
          <note>Antioxidationsmittel</note>
          <note>Phosphat</note>
          <note>Weizen</note>
          <note>Eier</note>
          <note>Erdnüsse</note>
          <note>Milch und Milchprodukte (inkl. Laktose)</note>
          <price role="student">1.45</price>
          <price role="employee">2.90</price>
          <price role="other">3.20</price>
        </meal>
      </category>
      <category name="Beilagen">
        <meal>
          <name>Gartengemüse</name>
          <note>grün (Ampel)</note>
          <note>vegan</note>
          <price role="student">0.60</price>
          <price role="employee">1.20</price>
          <price role="other">1.30</price>
        </meal>
        <meal>
          <name>Bratkartoffeln</name>
          <note>grün (Ampel)</note>
          <note>vegan</note>
          <price role="student">0.75</price>
          <price role="employee">1.50</price>
          <price role="other">1.65</price>
        </meal>
        <meal>
          <name>Dreikornrisotto</name>
          <note>gelb (Ampel)</note>
          <note>vegan</note>
          <note>Roggen</note>
          <note>Dinkel</note>
          <price role="student">0.60</price>
          <price role="employee">1.20</price>
          <price role="other">1.30</price>
        </meal>
      </category>
    </day>
    <day date="2020-03-12">
      <category name="Salate">
        <meal>
          <name>Große Salatschale</name>
          <note>grün (Ampel)</note>
          <note>vegan</note>
          <note>Süßungsmittel</note>
          <note>Sellerie</note>
          <price role="student">1.75</price>
          <price role="employee">3.50</price>
          <price role="other">3.85</price>
        </meal>
        <meal>
          <name>Kleine Salatschale</name>
          <note>grün (Ampel)</note>
          <note>vegan</note>
          <note>Süßungsmittel</note>
          <note>Sellerie</note>
          <price role="student">0.65</price>
          <price role="employee">1.30</price>
          <price role="other">1.45</price>
        </meal>
        <meal>
          <name>Joghurtdressing</name>
          <note>rot (Ampel)</note>
          <note>vegetarisch</note>
          <note>Antioxidationsmittel</note>
          <note>Weizen</note>
          <note>Eier</note>
          <note>Milch und Milchprodukte (inkl. Laktose)</note>
          <note>Schwefeldioxid und Sulfide</note>
          <note>Senf</note>
        </meal>
        <meal>
          <name>Sauce Vinaigrette</name>
          <note>rot (Ampel)</note>
          <note>vegan</note>
          <note>Senf</note>
        </meal>
      </category>
      <category name="Essen">
        <meal>
          <name>Hähnchengeschnetzeltes in Kokos-Curry-Sauce mit Gemüse</name>
          <note>gelb (Ampel)</note>
          <note>Soja</note>
          <price role="student">1.75</price>
          <price role="employee">3.50</price>
          <price role="other">3.85</price>
        </meal>
        <meal>
          <name>Eine vegetarische Frühlingsrolle</name>
          <note>rot (Ampel)</note>
          <note>vegetarisch</note>
          <note>Antioxidationsmittel</note>
          <note>Weizen</note>
          <note>Eier</note>
          <note>Sellerie</note>
          <note>Soja</note>
          <price role="student">1.55</price>
          <price role="employee">3.10</price>
          <price role="other">3.40</price>
        </meal>
        <meal>
          <name>Kartoffelgulasch mit saurer Sahne</name>
          <note>grün (Ampel)</note>
          <note>vegetarisch</note>
          <note>Antioxidationsmittel</note>
          <note>Sellerie</note>
          <note>Milch und Milchprodukte (inkl. Laktose)</note>
          <price role="student">1.45</price>
          <price role="employee">2.90</price>
          <price role="other">3.20</price>
        </meal>
      </category>
      <category name="Beilagen">
        <meal>
          <name>Paprika-Ingwer-Gemüse</name>
          <note>grün (Ampel)</note>
          <note>vegan</note>
          <price role="student">0.60</price>
          <price role="employee">1.20</price>
          <price role="other">1.30</price>
        </meal>
        <meal>
          <name>Kartoffelkroketten</name>
          <note>gelb (Ampel)</note>
          <note>vegetarisch</note>
          <note>Farbstoff</note>
          <note>Weizen</note>
          <note>Hefe</note>
          <price role="student">0.75</price>
          <price role="employee">1.50</price>
          <price role="other">1.65</price>
        </meal>
        <meal>
          <name>Basmatireis</name>
          <note>gelb (Ampel)</note>
          <note>vegan</note>
          <price role="student">0.60</price>
          <price role="employee">1.20</price>
          <price role="other">1.30</price>
        </meal>
      </category>
    </day>
    <day date="2020-03-13">
      <category name="Salate">
        <meal>
          <name>Große Salatschale</name>
          <note>grün (Ampel)</note>
          <note>vegan</note>
          <note>Süßungsmittel</note>
          <note>Sellerie</note>
          <price role="student">1.75</price>
          <price role="employee">3.50</price>
          <price role="other">3.85</price>
        </meal>
        <meal>
          <name>Kleine Salatschale</name>
          <note>grün (Ampel)</note>
          <note>vegan</note>
          <note>Süßungsmittel</note>
          <note>Sellerie</note>
          <price role="student">0.65</price>
          <price role="employee">1.30</price>
          <price role="other">1.45</price>
        </meal>
        <meal>
          <name>Joghurtdressing</name>
          <note>rot (Ampel)</note>
          <note>vegetarisch</note>
          <note>Antioxidationsmittel</note>
          <note>Weizen</note>
          <note>Eier</note>
          <note>Milch und Milchprodukte (inkl. Laktose)</note>
          <note>Schwefeldioxid und Sulfide</note>
          <note>Senf</note>
        </meal>
        <meal>
          <name>Sauce Vinaigrette</name>
          <note>rot (Ampel)</note>
          <note>vegan</note>
          <note>Senf</note>
        </meal>
      </category>
      <category name="Essen">
        <meal>
          <name>Ein Seelachsfilet mit Spinat und Käse überbacken an Kräuter-Sahne-Sauce</name>
          <note>gelb (Ampel)</note>
          <note>MSC</note>
          <note>Antioxidationsmittel</note>
          <note>Fisch</note>
          <note>Milch und Milchprodukte (inkl. Laktose)</note>
          <price role="student">2.45</price>
          <price role="employee">4.90</price>
          <price role="other">5.40</price>
        </meal>
        <meal>
          <name>Ein gebackener Kartoffelbratling mit Frischkäsefüllung an Paprikasauce</name>
          <note>gelb (Ampel)</note>
          <note>vegetarisch</note>
          <note>Antioxidationsmittel</note>
          <note>Weizen</note>
          <note>Milch und Milchprodukte (inkl. Laktose)</note>
          <note>Schwefeldioxid und Sulfide</note>
          <price role="student">1.35</price>
          <price role="employee">2.70</price>
          <price role="other">2.95</price>
        </meal>
        <meal>
          <name>Jambalaya mit Paprika, Sellerie, gerösteten Erdnüssen und Basmatireis</name>
          <note>grün (Ampel)</note>
          <note>vegan</note>
          <note>Erdnüsse</note>
          <note>Sellerie</note>
          <note>Soja</note>
          <price role="student">1.45</price>
          <price role="employee">2.90</price>
          <price role="other">3.20</price>
        </meal>
      </category>
      <category name="Beilagen">
        <meal>
          <name>Gemischtes Gemüse</name>
          <note>grün (Ampel)</note>
          <note>vegan</note>
          <price role="student">0.60</price>
          <price role="employee">1.20</price>
          <price role="other">1.30</price>
        </meal>
        <meal>
          <name>Rosmarinkartoffeln</name>
          <note>grün (Ampel)</note>
          <note>vegan</note>
          <price role="student">0.75</price>
          <price role="employee">1.50</price>
          <price role="other">1.65</price>
        </meal>
      </category>
    </day>
    <day date="2020-03-14">
      <closed></closed>
    </day>
    <day date="2020-03-15">
      <closed></closed>
    </day>
    <day date="2020-03-16">
      <category name="Salate">
        <meal>
          <name>Große Salatschale</name>
          <note>grün (Ampel)</note>
          <note>vegan</note>
          <note>Süßungsmittel</note>
          <note>Sellerie</note>
          <price role="student">1.75</price>
          <price role="employee">3.50</price>
          <price role="other">3.85</price>
        </meal>
        <meal>
          <name>Kleine Salatschale</name>
          <note>grün (Ampel)</note>
          <note>vegan</note>
          <note>Süßungsmittel</note>
          <note>Sellerie</note>
          <price role="student">0.65</price>
          <price role="employee">1.30</price>
          <price role="other">1.45</price>
        </meal>
        <meal>
          <name>Sauce Vinaigrette</name>
          <note>rot (Ampel)</note>
          <note>vegan</note>
          <note>Senf</note>
        </meal>
        <meal>
          <name>Joghurtdressing</name>
          <note>rot (Ampel)</note>
          <note>vegetarisch</note>
          <note>Antioxidationsmittel</note>
          <note>Weizen</note>
          <note>Eier</note>
          <note>Milch und Milchprodukte (inkl. Laktose)</note>
          <note>Schwefeldioxid und Sulfide</note>
          <note>Senf</note>
        </meal>
      </category>
      <category name="Essen">
        <meal>
          <name>Eine gebackene Hähnchenbrust Milano an Tomaten-Oliven-Sauce</name>
          <note>gelb (Ampel)</note>
          <note>Antioxidationsmittel</note>
          <note>Farbstoff</note>
          <note>geschwärzt</note>
          <note>Weizen</note>
          <note>Milch und Milchprodukte (inkl. Laktose)</note>
          <note>Schwefeldioxid und Sulfide</note>
          <note>Hefe</note>
          <price role="student">1.75</price>
          <price role="employee">3.50</price>
          <price role="other">3.85</price>
        </meal>
        <meal>
          <name>Kürbis-Chiasamen-Bratling an fruchtiger Tomatensauce</name>
          <note>grün (Ampel)</note>
          <note>vegetarisch</note>
          <note>Farbstoff</note>
          <note>Milch und Milchprodukte (inkl. Laktose)</note>
          <price role="student">1.35</price>
          <price role="employee">2.70</price>
          <price role="other">2.95</price>
        </meal>
        <meal>
          <name>Spanische Reispfanne mit buntem Gemüse</name>
          <note>grün (Ampel)</note>
          <note>vegan</note>
          <note>Antioxidationsmittel</note>
          <note>Farbstoff</note>
          <note>geschwärzt</note>
          <price role="student">1.45</price>
          <price role="employee">2.90</price>
          <price role="other">3.20</price>
        </meal>
      </category>
      <category name="Beilagen">
        <meal>
          <name>Schwarzwurzeln</name>
          <note>grün (Ampel)</note>
          <note>vegan</note>
          <note>Antioxidationsmittel</note>
          <price role="student">0.60</price>
          <price role="employee">1.20</price>
          <price role="other">1.30</price>
        </meal>
        <meal>
          <name>Rigatoni</name>
          <note>gelb (Ampel)</note>
          <note>vegan</note>
          <note>Weizen</note>
          <price role="student">0.60</price>
          <price role="employee">1.20</price>
          <price role="other">1.30</price>
        </meal>
        <meal>
          <name>Parboiledreis mit Dinkel</name>
          <note>gelb (Ampel)</note>
          <note>vegan</note>
          <note>Dinkel</note>
          <price role="student">0.60</price>
          <price role="employee">1.20</price>
          <price role="other">1.30</price>
        </meal>
      </category>
    </day>
    <day date="2020-03-17">
      <category name="Salate">
        <meal>
          <name>Große Salatschale</name>
          <note>grün (Ampel)</note>
          <note>vegan</note>
          <note>Süßungsmittel</note>
          <note>Sellerie</note>
          <price role="student">1.75</price>
          <price role="employee">3.50</price>
          <price role="other">3.85</price>
        </meal>
        <meal>
          <name>Kleine Salatschale</name>
          <note>grün (Ampel)</note>
          <note>vegan</note>
          <note>Süßungsmittel</note>
          <note>Sellerie</note>
          <price role="student">0.65</price>
          <price role="employee">1.30</price>
          <price role="other">1.45</price>
        </meal>
        <meal>
          <name>Joghurtdressing</name>
          <note>rot (Ampel)</note>
          <note>vegetarisch</note>
          <note>Antioxidationsmittel</note>
          <note>Weizen</note>
          <note>Eier</note>
          <note>Milch und Milchprodukte (inkl. Laktose)</note>
          <note>Schwefeldioxid und Sulfide</note>
          <note>Senf</note>
        </meal>
        <meal>
          <name>Sauce Vinaigrette</name>
          <note>rot (Ampel)</note>
          <note>vegan</note>
          <note>Senf</note>
        </meal>
      </category>
      <category name="Essen">
        <meal>
          <name>Ein gebackenes Gemüseschnitzel an Paprikasauce</name>
          <note>gelb (Ampel)</note>
          <note>vegan</note>
          <note>Weizen</note>
          <note>Dinkel</note>
          <note>Sellerie</note>
          <note>Soja</note>
          <note>Hefe</note>
          <price role="student">1.35</price>
          <price role="employee">2.70</price>
          <price role="other">2.95</price>
        </meal>
        <meal>
          <name>Hexenpolenta an Kräuter-Sahne-Sauce</name>
          <note>rot (Ampel)</note>
          <note>vegetarisch</note>
          <note>Antioxidationsmittel</note>
          <note>Mandeln</note>
          <note>Milch und Milchprodukte (inkl. Laktose)</note>
          <price role="student">1.45</price>
          <price role="employee">2.90</price>
          <price role="other">3.20</price>
        </meal>
      </category>
      <category name="Beilagen">
        <meal>
          <name>Brokkoli</name>
          <note>grün (Ampel)</note>
          <note>vegan</note>
          <price role="student">0.60</price>
          <price role="employee">1.20</price>
          <price role="other">1.30</price>
        </meal>
        <meal>
          <name>Kartoffeln</name>
          <note>grün (Ampel)</note>
          <note>vegan</note>
          <price role="student">0.60</price>
          <price role="employee">1.20</price>
          <price role="other">1.30</price>
        </meal>
      </category>
    </day>
  </canteen>
</openmensa>
